proj/button_driver.vhd
library ieee;
  use ieee.std_logic_1164.all;
  use ieee.numeric_std.all;


entity button_driver is
    port(
    clk         : in  std_logic;
    SW         : in  std_logic;
    rst         : in  std_logic;
    input       : in  std_logic;
    send       : in  std_logic;
    output      : out  std_logic_vector(20 downto 0);
    LED17_R : out STD_LOGIC;
    LED17_G : out STD_LOGIC;
    LED17_B : out STD_LOGIC
    );
end entity button_driver;

architecture Behavioral of button_driver is
    signal sig_out : std_logic_vector(20 downto 0);
    signal one_cnt : integer := 0;
    signal zero_cnt : integer := 0;
    begin
        p_button_driver : process (clk,input,send) is
            begin
                if rising_edge(clk) then--(SW = '1')
                    if (rst = '1') then
                        sig_out <= "000000000000000000000";
                        output <= (others => '0');
                        one_cnt <= 0;
                        LED17_G <= '0';
                        LED17_B <= '0';
                        LED17_R <= '0';
                    elsif (SW = '1') then
                        if (send = '1') then
                            output <= sig_out;
                            sig_out <= "000000000000000000000";
                        end if;
                        if (input = '0') then
                            zero_cnt <= zero_cnt + 1;
                            one_cnt <= 0;
                            LED17_G <= '1';
                            LED17_B <= '0';
                            LED17_R <= '0';
                        end if;
                        if (zero_cnt = 1) then
                            sig_out(20) <= sig_out(19);
                            sig_out(19) <= sig_out(18);
                            sig_out(18) <= sig_out(17);
                            sig_out(17) <= sig_out(16);
                            sig_out(16) <= sig_out(15);
                            sig_out(15) <= sig_out(14);
                            sig_out(14) <= sig_out(13);
                            sig_out(13) <= sig_out(12);
                            sig_out(12) <= sig_out(11);
                            sig_out(11) <= sig_out(10);
                            sig_out(10) <= sig_out(9);
                            sig_out(9) <= sig_out(8);
                            sig_out(8) <= sig_out(7);
                            sig_out(7) <= sig_out(6);
                            sig_out(6) <= sig_out(5);
                            sig_out(5) <= sig_out(4);
                            sig_out(4) <= sig_out(3);
                            sig_out(3) <= sig_out(2);
                            sig_out(2) <= sig_out(1);
                            sig_out(1) <= sig_out(0);
                            sig_out(0) <= '0';
                        end if;
                        if (input = '1') then
                            zero_cnt <= 0;
                            one_cnt <= one_cnt + 1;
                            if (one_cnt < 2) then
                                LED17_G <= '0';
                                LED17_B <= '0';
                                LED17_R <= '1';
                            elsif (one_cnt = 2) then
                                LED17_G <= '0';
                                LED17_B <= '1';
                                LED17_R <= '0';
                            elsif (one_cnt > 2) then
                                LED17_G <= '0';
                                LED17_B <= '1';
                                LED17_R <= '0';
                            end if;
                        end if;
                        if (one_cnt = 1) then
                            sig_out(20) <= sig_out(19);
                            sig_out(19) <= sig_out(18);
                            sig_out(18) <= sig_out(17);
                            sig_out(17) <= sig_out(16);
                            sig_out(16) <= sig_out(15);
                            sig_out(15) <= sig_out(14);
                            sig_out(14) <= sig_out(13);
                            sig_out(13) <= sig_out(12);
                            sig_out(12) <= sig_out(11);
                            sig_out(11) <= sig_out(10);
                            sig_out(10) <= sig_out(9);
                            sig_out(9) <= sig_out(8);
                            sig_out(8) <= sig_out(7);
                            sig_out(7) <= sig_out(6);
                            sig_out(6) <= sig_out(5);
                            sig_out(5) <= sig_out(4);
                            sig_out(4) <= sig_out(3);
                            sig_out(3) <= sig_out(2);
                            sig_out(2) <= sig_out(1);
                            sig_out(1) <= sig_out(0);
                            sig_out(0) <= '1';
                        elsif (one_cnt = 3) then
                            sig_out(20) <= sig_out(18);
                            sig_out(19) <= sig_out(17);
                            sig_out(18) <= sig_out(16);
                            sig_out(17) <= sig_out(15);
                            sig_out(16) <= sig_out(14);
                            sig_out(15) <= sig_out(13);
                            sig_out(14) <= sig_out(12);
                            sig_out(13) <= sig_out(11);
                            sig_out(12) <= sig_out(10);
                            sig_out(11) <= sig_out(9);
                            sig_out(10) <= sig_out(8);
                            sig_out(9) <= sig_out(7);
                            sig_out(8) <= sig_out(6);
                            sig_out(7) <= sig_out(5);
                            sig_out(6) <= sig_out(4);
                            sig_out(5) <= sig_out(3);
                            sig_out(4) <= sig_out(2);
                            sig_out(3) <= sig_out(1);
                            sig_out(2) <= sig_out(0);
                            sig_out(1) <= '1';
                            sig_out(0) <= '1';
                        end if;
                    else 
                    sig_out <= "000000000000000000000";
                    output <= (others => '0');
                    one_cnt <= 0;
                    LED17_G <= '0';
                    LED17_B <= '0';
                    LED17_R <= '0';
                    end if;
                end if;
            end process p_button_driver;
    end architecture Behavioral;

tb_mux_driver.vhd
library ieee;
  use ieee.std_logic_1164.all;
  use ieee.numeric_std.all;


entity tb_button_driver is
--  Port ( );
end tb_button_driver;

architecture testbench of tb_button_driver is

    constant c_CLK_100MHZ_PERIOD : time := 10 ns;

    signal SW                : std_logic;
    signal rst               : std_logic;
    signal sig_clk_100mhz    : std_logic;
    signal input             : std_logic;
    signal send              : std_logic;
    signal output            : std_logic_vector(20 downto 0);
    signal LED17_R :  STD_LOGIC;
    signal LED17_G :  STD_LOGIC;
    signal LED17_B :  STD_LOGIC;


begin
    uut_button_driver: entity work.button_driver
        port map(
            SW         => SW,
            rst        => rst,
            clk        => sig_clk_100mhz,
            input      => input,
            output     => output,
            send       => send,
            LED17_R    => LED17_R,
            LED17_G    => LED17_G,
            LED17_B    => LED17_B
        );
        
    p_clk_gen : process is
    begin
          
        while now < 2000 ns loop -- 200 periods of 100MHz clock
          
             sig_clk_100mhz <= '0';
             wait for c_CLK_100MHZ_PERIOD / 2;
             sig_clk_100mhz <= '1';
             wait for c_CLK_100MHZ_PERIOD / 2;
          
        end loop;
        wait;
          
    end process p_clk_gen;

    p_reset_gen : process is
    begin
      
        rst <= '0';
        wait for 10 ns;
        rst <= '1';
        wait for 90 ns;
        rst <= '0';
        wait for 1500 ns;
        rst <= '1';
        wait for 90 ns;
        rst <= '0';
        wait;
      
    end process p_reset_gen;

    p_SW : process is
        begin
            SW <= '1';
            wait;
        end process p_SW;

    p_send : process is
        begin
          
            send <= '0';
            wait for 300 ns;
            send <= '1';
            wait for 10 ns;
            send <= '0';
            wait for 220 ns;
            send <= '1';
            wait for 10 ns;
            send <= '0';
            wait for 220 ns;
            send <= '1';
            wait for 10 ns;
            send <= '0';
            wait for 190 ns;
            send <= '1';
            wait for 10 ns;
            send <= '0';
            wait for 200 ns;
            send <= '1';
            wait for 10 ns;
            send <= '0';
            wait for 370 ns;
            send <= '1';
            wait for 10 ns;
            send <= '0';
            wait;
          
    end process p_send;

    p_stimulus : process
    begin
    	input <= '0';
        wait for 200 ns; -- NO INPUT
        input <= '1';
        wait for 25 ns; --longer
        input <= '0';
        wait for 10 ns; -- A
        input <= '1';
        wait for 50 ns; --longer
        input <= '0';
        wait for 100 ns; -- Pause --longer
        input <= '1';
        wait for 30 ns;
        input <= '0';
        wait for 10 ns;
        input <= '1';
        wait for 25 ns; --longer
        input <= '0';
        wait for 10 ns; -- B
        input <= '1';
        wait for 10 ns;
        input <= '0';
        wait for 10 ns;
        input <= '1';
        wait for 25 ns; --longer
        input <= '0';
        wait for 50 ns; -- Pause --longer
        input <= '1';
        wait for 30 ns;
        input <= '0';
        wait for 10 ns;
        input <= '1';
        wait for 25 ns; --longer
        input <= '0';
        wait for 10 ns; -- C
        input <= '1';
        wait for 60 ns; --longer
        input <= '0';
        wait for 10 ns;
        input <= '1';
        wait for 27 ns; --longer
        input <= '0';
        wait for 70 ns; -- Pause --longer
        input <= '1';
        wait for 25 ns; --longer
        input <= '0';
        wait for 10 ns;
        input <= '1';
        wait for 30 ns;
        input <= '0';
        wait for 10 ns; -- J
        input <= '1';
        wait for 30 ns;
        input <= '0';
        wait for 10 ns;
        input <= '1';
        wait for 30 ns;
        input <= '0';
        wait for 50 ns; -- Pause --longer
        input <= '1';
        wait for 30 ns;
        input <= '0';
        wait for 10 ns;
        input <= '1';
        wait for 60 ns; -- O --longer
        input <= '0';
        wait for 10 ns;
        input <= '1';
        wait for 50 ns; --longer
        input <= '0';
        wait for 30 ns; -- Pause
        input <= '1';
        wait for 30 ns;
        input <= '0';
        wait for 10 ns;
        input <= '1';
        wait for 50 ns; -- 0 --longer
        input <= '0';
        wait for 10 ns;
        input <= '1';
        wait for 70 ns; --longer
        input <= '0';
        wait for 10 ns;
        input <= '1';
        wait for 30 ns; 
        input <= '0';
        wait for 10 ns;
        input <= '1';
        wait for 70 ns; --longer
        input <= '0';
        wait for 150 ns; -- Pause --longer
        wait;
    end process p_stimulus;
end architecture testbench;

sim/button_driver.vcd
$date
  Thu Apr 13 15:30:51 2023
$end
$version
  GHDL v0
$end
$timescale
  1 fs
$end
$scope module standard $end
$upscope $end
$scope module std_logic_1164 $end
$upscope $end
$scope module numeric_std $end
$upscope $end
$scope module tb_button_driver $end
$var reg 1 ! sw $end
$var reg 1 " rst $end
$var reg 1 # sig_clk_100mhz $end
$var reg 1 $ input $end
$var reg 1 % send $end
$var reg 21 & output[20:0] $end
$var reg 1 ' led17_r $end
$var reg 1 ( led17_g $end
$var reg 1 ) led17_b $end
$scope module uut_button_driver $end
$var reg 1 * clk $end
$var reg 1 + sw $end
$var reg 1 , rst $end
$var reg 1 - input $end
$var reg 1 . send $end
$var reg 21 / output[20:0] $end
$var reg 1 0 led17_r $end
$var reg 1 1 led17_g $end
$var reg 1 2 led17_b $end
$var reg 21 3 sig_out[20:0] $end
$var integer 32 4 one_cnt $end
$var integer 32 5 zero_cnt $end
$upscope $end
$upscope $end
$enddefinitions $end
#0
1!
0"
0#
0$
0%
b000000000000000000000 &
0'
0(
0)
0*
1+
0,
0-
0.
b000000000000000000000 /
00
01
02
b000000000000000000000 3
b0 4
b0 5
#5000000
1#
1(
1*
11
b1 5
#10000000
1"
0#
0(
0*
1,
01
#15000000
1#
1*
#20000000
0#
0*
#25000000
1#
1*
#30000000
0#
0*
#35000000
1#
1*
#40000000
0#
0*
#45000000
1#
1*
#50000000
0#
0*
#55000000
1#
1*
#60000000
0#
0*
#65000000
1#
1*
#70000000
0#
0*
#75000000
1#
1*
#80000000
0#
0*
#85000000
1#
1*
#90000000
0#
0*
#95000000
1#
1*
#100000000
0"
0#
0*
0,
#105000000
1#
1(
1*
11
b10 5
#110000000
0#
0*
#115000000
1#
1*
b11 5
#120000000
0#
0*
#125000000
1#
1*
b100 5
#130000000
0#
0*
#135000000
1#
1*
b101 5
#140000000
0#
0*
#145000000
1#
1*
b110 5
#150000000
0#
0*
#155000000
1#
1*
b111 5
#160000000
0#
0*
#165000000
1#
1*
b1000 5
#170000000
0#
0*
#175000000
1#
1*
b1001 5
#180000000
0#
0*
#185000000
1#
1*
b1010 5
#190000000
0#
0*
#195000000
1#
1*
b1011 5
#200000000
0#
1$
0*
1-
#205000000
1#
1'
0(
1*
10
01
b1 4
b0 5
#210000000
0#
0*
#215000000
1#
1*
b000000000000000000001 3
b10 4
#220000000
0#
0*
#225000000
1#
0$
0'
1(
1*
0-
00
11
b0 4
b1 5
#230000000
0#
0*
#235000000
1#
1$
1'
0(
1*
1-
10
01
b000000000000000000010 3
b1 4
b0 5
#240000000
0#
0*
#245000000
1#
1*
b000000000000000000101 3
b10 4
#250000000
0#
0*
#255000000
1#
0'
1)
1*
00
12
b11 4
#260000000
0#
0*
#265000000
1#
1*
b000000000000000010111 3
b100 4
#270000000
0#
0*
#275000000
1#
1*
b101 4
#280000000
0#
0*
#285000000
1#
0$
1(
0)
1*
0-
11
02
b0 4
b1 5
#290000000
0#
0*
#295000000
1#
1*
b000000000000000101110 3
b10 5
#300000000
0#
1%
0*
1.
#305000000
1#
b000000000000000101110 &
1*
b000000000000000101110 /
b000000000000000000000 3
b11 5
#310000000
0#
0%
0*
0.
#315000000
1#
1*
b100 5
#320000000
0#
0*
#325000000
1#
1*
b101 5
#330000000
0#
0*
#335000000
1#
1*
b110 5
#340000000
0#
0*
#345000000
1#
1*
b111 5
#350000000
0#
0*
#355000000
1#
1*
b1000 5
#360000000
0#
0*
#365000000
1#
1*
b1001 5
#370000000
0#
0*
#375000000
1#
1*
b1010 5
#380000000
0#
0*
#385000000
1#
1$
1'
0(
1*
1-
10
01
b1 4
b0 5
#390000000
0#
0*
#395000000
1#
1*
b000000000000000000001 3
b10 4
#400000000
0#
0*
#405000000
1#
0'
1)
1*
00
12
b11 4
#410000000
0#
0*
#415000000
1#
0$
1(
0)
1*
0-
11
02
b000000000000000000111 3
b0 4
b1 5
#420000000
0#
0*
#425000000
1#
1$
1'
0(
1*
1-
10
01
b000000000000000001110 3
b1 4
b0 5
#430000000
0#
0*
#435000000
1#
1*
b000000000000000011101 3
b10 4
#440000000
0#
0*
#445000000
1#
0'
1)
1*
00
12
b11 4
#450000000
0#
0$
0*
0-
#455000000
1#
1(
0)
1*
11
02
b000000000000001110111 3
b0 4
b1 5
#460000000
0#
1$
0*
1-
#465000000
1#
1'
0(
1*
10
01
b000000000000011101110 3
b1 4
b0 5
#470000000
0#
0$
0*
0-
#475000000
1#
0'
1(
1*
00
11
b000000000000111011101 3
b0 4
b1 5
#480000000
0#
1$
0*
1-
#485000000
1#
1'
0(
1*
10
01
b000000000001110111010 3
b1 4
b0 5
#490000000
0#
0*
#495000000
1#
1*
b000000000011101110101 3
b10 4
#500000000
0#
0*
#505000000
1#
0$
0'
1(
1*
0-
00
11
b0 4
b1 5
#510000000
0#
0*
#515000000
1#
1*
b000000000111011101010 3
b10 5
#520000000
0#
0*
#525000000
1#
1*
b11 5
#530000000
0#
1%
0*
1.
#535000000
1#
b000000000111011101010 &
1*
b000000000111011101010 /
b000000000000000000000 3
b100 5
#540000000
0#
0%
0*
0.
#545000000
1#
1*
b101 5
#550000000
0#
0*
#555000000
1#
1$
1'
0(
1*
1-
10
01
b1 4
b0 5
#560000000
0#
0*
#565000000
1#
1*
b000000000000000000001 3
b10 4
#570000000
0#
0*
#575000000
1#
0'
1)
1*
00
12
b11 4
#580000000
0#
0*
#585000000
1#
0$
1(
0)
1*
0-
11
02
b000000000000000000111 3
b0 4
b1 5
#590000000
0#
0*
#595000000
1#
1$
1'
0(
1*
1-
10
01
b000000000000000001110 3
b1 4
b0 5
#600000000
0#
0*
#605000000
1#
1*
b000000000000000011101 3
b10 4
#610000000
0#
0*
#615000000
1#
0'
1)
1*
00
12
b11 4
#620000000
0#
0$
0*
0-
#625000000
1#
1(
0)
1*
11
02
b000000000000001110111 3
b0 4
b1 5
#630000000
0#
1$
0*
1-
#635000000
1#
1'
0(
1*
10
01
b000000000000011101110 3
b1 4
b0 5
#640000000
0#
0*
#645000000
1#
1*
b000000000000111011101 3
b10 4
#650000000
0#
0*
#655000000
1#
0'
1)
1*
00
12
b11 4
#660000000
0#
0*
#665000000
1#
1*
b000000000011101110111 3
b100 4
#670000000
0#
0*
#675000000
1#
1*
b101 4
#680000000
0#
0*
#685000000
1#
1*
b110 4
#690000000
0#
0$
0*
0-
#695000000
1#
1(
0)
1*
11
02
b0 4
b1 5
#700000000
0#
1$
0*
1-
#705000000
1#
1'
0(
1*
10
01
b000000000111011101110 3
b1 4
b0 5
#710000000
0#
0*
#715000000
1#
1*
b000000001110111011101 3
b10 4
#720000000
0#
0*
#725000000
1#
0'
1)
1*
00
12
b11 4
#727000000
0$
0-
#730000000
0#
0*
#735000000
1#
1(
0)
1*
11
02
b000000111011101110111 3
b0 4
b1 5
#740000000
0#
0*
#745000000
1#
1*
b000001110111011101110 3
b10 5
#750000000
0#
0*
#755000000
1#
1*
b11 5
#760000000
0#
1%
0*
1.
#765000000
1#
b000001110111011101110 &
1*
b000001110111011101110 /
b000000000000000000000 3
b100 5
#770000000
0#
0%
0*
0.
#775000000
1#
1*
b101 5
#780000000
0#
0*
#785000000
1#
1*
b110 5
#790000000
0#
0*
#795000000
1#
1*
b111 5
#797000000
1$
1-
#800000000
0#
0*
#805000000
1#
1'
0(
1*
10
01
b1 4
b0 5
#810000000
0#
0*
#815000000
1#
1*
b000000000000000000001 3
b10 4
#820000000
0#
0*
#822000000
0$
0-
#825000000
1#
0'
1(
1*
00
11
b0 4
b1 5
#830000000
0#
0*
#832000000
1$
1-
#835000000
1#
1'
0(
1*
10
01
b000000000000000000010 3
b1 4
b0 5
#840000000
0#
0*
#845000000
1#
1*
b000000000000000000101 3
b10 4
#850000000
0#
0*
#855000000
1#
0'
1)
1*
00
12
b11 4
#860000000
0#
0*
#862000000
0$
0-
#865000000
1#
1(
0)
1*
11
02
b000000000000000010111 3
b0 4
b1 5
#870000000
0#
0*
#872000000
1$
1-
#875000000
1#
1'
0(
1*
10
01
b000000000000000101110 3
b1 4
b0 5
#880000000
0#
0*
#885000000
1#
1*
b000000000000001011101 3
b10 4
#890000000
0#
0*
#895000000
1#
0'
1)
1*
00
12
b11 4
#900000000
0#
0*
#902000000
0$
0-
#905000000
1#
1(
0)
1*
11
02
b000000000000101110111 3
b0 4
b1 5
#910000000
0#
0*
#912000000
1$
1-
#915000000
1#
1'
0(
1*
10
01
b000000000001011101110 3
b1 4
b0 5
#920000000
0#
0*
#925000000
1#
1*
b000000000010111011101 3
b10 4
#930000000
0#
0*
#935000000
1#
0'
1)
1*
00
12
b11 4
#940000000
0#
0*
#942000000
0$
0-
#945000000
1#
1(
0)
1*
11
02
b000000001011101110111 3
b0 4
b1 5
#950000000
0#
0*
#955000000
1#
1*
b000000010111011101110 3
b10 5
#960000000
0#
1%
0*
1.
#965000000
1#
b000000010111011101110 &
1*
b000000010111011101110 /
b000000000000000000000 3
b11 5
#970000000
0#
0%
0*
0.
#975000000
1#
1*
b100 5
#980000000
0#
0*
#985000000
1#
1*
b101 5
#990000000
0#
0*
#992000000
1$
1-
#995000000
1#
1'
0(
1*
10
01
b1 4
b0 5
#1000000000
0#
0*
#1005000000
1#
1*
b000000000000000000001 3
b10 4
#1010000000
0#
0*
#1015000000
1#
0'
1)
1*
00
12
b11 4
#1020000000
0#
0*
#1022000000
0$
0-
#1025000000
1#
1(
0)
1*
11
02
b000000000000000000111 3
b0 4
b1 5
#1030000000
0#
0*
#1032000000
1$
1-
#1035000000
1#
1'
0(
1*
10
01
b000000000000000001110 3
b1 4
b0 5
#1040000000
0#
0*
#1045000000
1#
1*
b000000000000000011101 3
b10 4
#1050000000
0#
0*
#1055000000
1#
0'
1)
1*
00
12
b11 4
#1060000000
0#
0*
#1065000000
1#
1*
b000000000000001110111 3
b100 4
#1070000000
0#
0*
#1075000000
1#
1*
b101 4
#1080000000
0#
0*
#1085000000
1#
1*
b110 4
#1090000000
0#
0*
#1092000000
0$
0-
#1095000000
1#
1(
0)
1*
11
02
b0 4
b1 5
#1100000000
0#
0*
#1102000000
1$
1-
#1105000000
1#
1'
0(
1*
10
01
b000000000000011101110 3
b1 4
b0 5
#1110000000
0#
0*
#1115000000
1#
1*
b000000000000111011101 3
b10 4
#1120000000
0#
0*
#1125000000
1#
0'
1)
1*
00
12
b11 4
#1130000000
0#
0*
#1135000000
1#
1*
b000000000011101110111 3
b100 4
#1140000000
0#
0*
#1145000000
1#
1*
b101 4
#1150000000
0#
0*
#1152000000
0$
0-
#1155000000
1#
1(
0)
1*
11
02
b0 4
b1 5
#1160000000
0#
0*
#1165000000
1#
1*
b000000000111011101110 3
b10 5
#1170000000
0#
1%
0*
1.
#1175000000
1#
b000000000111011101110 &
1*
b000000000111011101110 /
b000000000000000000000 3
b11 5
#1180000000
0#
0%
0*
0.
#1182000000
1$
1-
#1185000000
1#
1'
0(
1*
10
01
b1 4
b0 5
#1190000000
0#
0*
#1195000000
1#
1*
b000000000000000000001 3
b10 4
#1200000000
0#
0*
#1205000000
1#
0'
1)
1*
00
12
b11 4
#1210000000
0#
0*
#1212000000
0$
0-
#1215000000
1#
1(
0)
1*
11
02
b000000000000000000111 3
b0 4
b1 5
#1220000000
0#
0*
#1222000000
1$
1-
#1225000000
1#
1'
0(
1*
10
01
b000000000000000001110 3
b1 4
b0 5
#1230000000
0#
0*
#1235000000
1#
1*
b000000000000000011101 3
b10 4
#1240000000
0#
0*
#1245000000
1#
0'
1)
1*
00
12
b11 4
#1250000000
0#
0*
#1255000000
1#
1*
b000000000000001110111 3
b100 4
#1260000000
0#
0*
#1265000000
1#
1*
b101 4
#1270000000
0#
0*
#1272000000
0$
0-
#1275000000
1#
1(
0)
1*
11
02
b0 4
b1 5
#1280000000
0#
0*
#1282000000
1$
1-
#1285000000
1#
1'
0(
1*
10
01
b000000000000011101110 3
b1 4
b0 5
#1290000000
0#
0*
#1295000000
1#
1*
b000000000000111011101 3
b10 4
#1300000000
0#
0*
#1305000000
1#
0'
1)
1*
00
12
b11 4
#1310000000
0#
0*
#1315000000
1#
1*
b000000000011101110111 3
b100 4
#1320000000
0#
0*
#1325000000
1#
1*
b101 4
#1330000000
0#
0*
#1335000000
1#
1*
b110 4
#1340000000
0#
0*
#1345000000
1#
1*
b111 4
#1350000000
0#
0*
#1352000000
0$
0-
#1355000000
1#
1(
0)
1*
11
02
b0 4
b1 5
#1360000000
0#
0*
#1362000000
1$
1-
#1365000000
1#
1'
0(
1*
10
01
b000000000111011101110 3
b1 4
b0 5
#1370000000
0#
0*
#1375000000
1#
1*
b000000001110111011101 3
b10 4
#1380000000
0#
0*
#1385000000
1#
0'
1)
1*
00
12
b11 4
#1390000000
0#
0*
#1392000000
0$
0-
#1395000000
1#
1(
0)
1*
11
02
b000000111011101110111 3
b0 4
b1 5
#1400000000
0#
0*
#1402000000
1$
1-
#1405000000
1#
1'
0(
1*
10
01
b000001110111011101110 3
b1 4
b0 5
#1410000000
0#
0*
#1415000000
1#
1*
b000011101110111011101 3
b10 4
#1420000000
0#
0*
#1425000000
1#
0'
1)
1*
00
12
b11 4
#1430000000
0#
0*
#1435000000
1#
1*
b001110111011101110111 3
b100 4
#1440000000
0#
0*
#1445000000
1#
1*
b101 4
#1450000000
0#
0*
#1455000000
1#
1*
b110 4
#1460000000
0#
0*
#1465000000
1#
1*
b111 4
#1470000000
0#
0*
#1472000000
0$
0-
#1475000000
1#
1(
0)
1*
11
02
b0 4
b1 5
#1480000000
0#
0*
#1485000000
1#
1*
b011101110111011101110 3
b10 5
#1490000000
0#
0*
#1495000000
1#
1*
b11 5
#1500000000
0#
0*
#1505000000
1#
1*
b100 5
#1510000000
0#
0*
#1515000000
1#
1*
b101 5
#1520000000
0#
0*
#1525000000
1#
1*
b110 5
#1530000000
0#
0*
#1535000000
1#
1*
b111 5
#1540000000
0#
0*
#1545000000
1#
1*
b1000 5
#1550000000
0#
1%
0*
1.
#1555000000
1#
b011101110111011101110 &
1*
b011101110111011101110 /
b000000000000000000000 3
b1001 5
#1560000000
0#
0%
0*
0.
#1565000000
1#
1*
b1010 5
#1570000000
0#
0*
#1575000000
1#
1*
b1011 5
#1580000000
0#
0*
#1585000000
1#
1*
b1100 5
#1590000000
0#
0*
#1595000000
1#
1*
b1101 5
#1600000000
1"
0#
b000000000000000000000 &
0(
0*
1,
b000000000000000000000 /
01
#1605000000
1#
1*
#1610000000
0#
0*
#1615000000
1#
1*
#1620000000
0#
0*
#1622000000
#1625000000
1#
1*
#1630000000
0#
0*
#1635000000
1#
1*
#1640000000
0#
0*
#1645000000
1#
1*
#1650000000
0#
0*
#1655000000
1#
1*
#1660000000
0#
0*
#1665000000
1#
1*
#1670000000
0#
0*
#1675000000
1#
1*
#1680000000
0#
0*
#1685000000
1#
1*
#1690000000
0"
0#
0*
0,
#1695000000
1#
1(
1*
11
b1110 5
#1700000000
0#
0*
#1705000000
1#
1*
b1111 5
#1710000000
0#
0*
#1715000000
1#
1*
b10000 5
#1720000000
0#
0*
#1725000000
1#
1*
b10001 5
#1730000000
0#
0*
#1735000000
1#
1*
b10010 5
#1740000000
0#
0*
#1745000000
1#
1*
b10011 5
#1750000000
0#
0*
#1755000000
1#
1*
b10100 5
#1760000000
0#
0*
#1765000000
1#
1*
b10101 5
#1770000000
0#
0*
#1775000000
1#
1*
b10110 5
#1780000000
0#
0*
#1785000000
1#
1*
b10111 5
#1790000000
0#
0*
#1795000000
1#
1*
b11000 5
#1800000000
0#
0*
#1805000000
1#
1*
b11001 5
#1810000000
0#
0*
#1815000000
1#
1*
b11010 5
#1820000000
0#
0*
#1825000000
1#
1*
b11011 5
#1830000000
0#
0*
#1835000000
1#
1*
b11100 5
#1840000000
0#
0*
#1845000000
1#
1*
b11101 5
#1850000000
0#
0*
#1855000000
1#
1*
b11110 5
#1860000000
0#
0*
#1865000000
1#
1*
b11111 5
#1870000000
0#
0*
#1875000000
1#
1*
b100000 5
#1880000000
0#
0*
#1885000000
1#
1*
b100001 5
#1890000000
0#
0*
#1895000000
1#
1*
b100010 5
#1900000000
0#
0*
#1905000000
1#
1*
b100011 5
#1910000000
0#
0*
#1915000000
1#
1*
b100100 5
#1920000000
0#
0*
#1925000000
1#
1*
b100101 5
#1930000000
0#
0*
#1935000000
1#
1*
b100110 5
#1940000000
0#
0*
#1945000000
1#
1*
b100111 5
#1950000000
0#
0*
#1955000000
1#
1*
b101000 5
#1960000000
0#
0*
#1965000000
1#
1*
b101001 5
#1970000000
0#
0*
#1975000000
1#
1*
b101010 5
#1980000000
0#
0*
#1985000000
1#
1*
b101011 5
#1990000000
0#
0*
#1995000000
1#
1*
b101100 5
