seg_driver_hex.vhd
----------------------------------------------------------------------------------
-- Company: 
-- Engineer: 
-- 
-- Create Date: 28.02.2023 13:19:23
-- Design Name: 
-- Module Name: hex_7seg - Behavioral
-- Project Name: 
-- Target Devices: 
-- Tool Versions: 
-- Description: 
-- 
-- Dependencies: 
-- 
-- Revision:
-- Revision 0.01 - File Created
-- Additional Comments:
-- 
----------------------------------------------------------------------------------


library IEEE;
use IEEE.STD_LOGIC_1164.ALL;

-- Uncomment the following library declaration if using
-- arithmetic functions with Signed or Unsigned values
--use IEEE.NUMERIC_STD.ALL;

-- Uncomment the following library declaration if instantiating
-- any Xilinx leaf cells in this code.
--library UNISIM;
--use UNISIM.VComponents.all;

entity hex_7seg is
    Port ( blank : in STD_LOGIC;
           hex : in STD_LOGIC_VECTOR (20 downto 0);
           seg : out STD_LOGIC_VECTOR (6 downto 0));
end hex_7seg;

architecture Behavioral of hex_7seg is

begin

  --------------------------------------------------------
  -- p_7seg_decoder:
  -- A combinational process for 7-segment display (Common
  -- Anode) decoder. Any time "hex" or "blank" is changed,
  -- the process is "executed". Output pin seg(6) controls
  -- segment A, seg(5) segment B, etc.
  --     segment A
  --      | segment B
  --      |  | segment C
  --      +-+|  |   ...   segment G
  --        ||+-+          |
  --        |||            |
  -- seg = "0000001"-------+
  --
  -- Display is clear/blank if signal blank = 1.
  --------------------------------------------------------

  p_7seg_decoder : process (blank, hex) is

  begin
    if (blank = '1') then
      seg <= "1111111";     -- Blanking display
    else

      case hex is
        when "000000000000000101110" =>
          seg <= "0001000"; -- A
          
        when "000000000001110101010" =>
          seg <= "1100000"; -- B
          
        when "000000000111010111010" =>
          seg <= "0110001"; -- C
          
        when "000000000000011101010" =>
          seg <= "1000010"; -- D
          
        when "000000000000000000010" =>
          seg <= "0110000"; -- E
         
         when "000000000001010111010" =>
          seg <= "0111000"; -- F
          
         when "000000000001110111010" =>
          seg <= "0100001"; -- G
          
         when "000000000000010101010" =>
          seg <= "1101000"; -- H
         
         when "000000000000000001010" =>
          seg <= "1001111"; -- I
         
         when "000000010111011101110" =>
          seg <= "1000011"; -- J
          
         when "000000000001110101110" =>
          seg <= "0101000"; -- K
          
         when "000000000001011101010" =>
          seg <= "1110001"; -- L
          
         when "000000000000011101110" =>
          seg <= "0101011"; -- M
          
         when "000000000000000111010" =>
          seg <= "1101010"; -- N
          
         when "000000000111011101110" =>
          seg <= "1100010"; -- O
         
         when "000000000101110111010" =>
          seg <= "0011000"; -- P
          
         when "000000011101110101110" =>
          seg <= "0001100"; -- Q
          
         when "000000000000010111010" =>
          seg <= "1111010"; -- R
          
         when "000000000000000101010" =>
          seg <= "0100101"; -- S
          
         when "000000000000000001110" =>
          seg <= "1110000"; -- T
         
         when "000000000000010101110" =>
          seg <= "1000001"; -- U
          
         when "000000000001010101110" =>
          seg <= "1100011"; -- V
          
         when "000000000001011101110" =>
          seg <= "1010101"; -- W
          
         when "000000000111010101110" =>
          seg <= "1001000"; -- X
          
         when "000000011101011101110" =>
          seg <= "1000100"; -- Y
          
         when "000000000111011101010" =>
          seg <= "0010011"; -- Z
          
         when "000101110111011101110" =>
          seg <= "1111001"; -- 1
          
         when "000001010111011101110" =>
          seg <= "0010010"; -- 2
         
         when "000000010101011101110" =>
          seg <= "0000110"; -- 3
          
         when "000000000101010101110" =>
          seg <= "1001100"; -- 4
         
         when "000000000001010101010" =>
          seg <= "0100100"; -- 5
          
         when "000000000111010101010" =>
          seg <= "0100000"; -- 6
          
         when "000000011101110101010" =>
          seg <= "0001111"; -- 7
          
         when "000001110111011101010" =>
          seg <= "0000000"; -- 8
          
         when "000111011101110111010" =>
          seg <= "0000100"; -- 9
          
         when "011101110111011101110" =>
          seg <= "0000001"; -- 0
          
         when "000000000000000000000" =>
          seg <= "1111111";  
          
         when others =>

          seg <= "1111110"; -- -

      end case;

    end if;

  end process p_7seg_decoder;

end Behavioral;

proj/cnt_up_down.vhd

library ieee;
  use ieee.std_logic_1164.all;
  use ieee.numeric_std.all;

----------------------------------------------------------
-- Entity declaration for N-bit counter
----------------------------------------------------------

entity cnt_up_down is
  generic (
    g_CNT_WIDTH : natural := 3 --! Default number of counter bits
  );
  port (
    clk    : in    std_logic; --! Main clock
    rst    : in    std_logic; --! Synchronous reset
    en     : in    std_logic; --! Enable input
    cnt_up : in    std_logic; --! Direction of the counter
    cnt    : out   std_logic_vector(g_CNT_WIDTH - 1 downto 0)
  );
end entity cnt_up_down;

----------------------------------------------------------
-- Architecture body for N-bit counter
----------------------------------------------------------

architecture behavioral of cnt_up_down is

  signal sig_cnt : unsigned(g_CNT_WIDTH - 1 downto 0); --! Local counter

begin

  --------------------------------------------------------
  -- p_cnt_up_down:
  -- Clocked process with synchronous reset which implements
  -- n-bit up/down counter.
  --------------------------------------------------------
  p_cnt_up_down : process (clk) is
  begin

    if rising_edge(clk) then
      if (rst = '1') then           -- Synchronous reset
        sig_cnt <= (others => '0'); -- Clear all bits
      elsif (en = '1') then         -- Test if counter is enabled

        -- TEST COUNTER DIRECTION HERE
        if (cnt_up = '1') then 
           sig_cnt <= sig_cnt + 1;
        else 
           sig_cnt <= sig_cnt - 1;
        end if;
      end if;
  end if;

 end process p_cnt_up_down;

  -- Output must be retyped from "unsigned" to "std_logic_vector"
  cnt <= std_logic_vector(sig_cnt);

end architecture behavioral;

src/clock_enable.vhd

----------------------------------------------------------
library ieee;
  use ieee.std_logic_1164.all;
  use ieee.numeric_std.all; -- Package for arithmetic operations

----------------------------------------------------------
-- Entity declaration for clock enable
----------------------------------------------------------

entity clock_enable is
  generic (
    g_MAX : natural := 200000 --! Number of clk pulses to generate one enable signal period
  );                       -- Note that there IS a semicolon between generic and port sections
  port (
    clk : in    std_logic; --! Main clock
    rst : in    std_logic; --! High-active synchronous reset
    ce  : out   std_logic  --! Clock enable pulse signal
  );
end entity clock_enable;

------------------------------------------------------------
-- Architecture body for clock enable
------------------------------------------------------------

architecture behavioral of clock_enable is

  -- Local counter
  signal sig_cnt : natural;

begin

  --------------------------------------------------------
  -- p_clk_enable:
  -- Generate clock enable signal. By default, enable signal
  -- is low and generated pulse is always one clock long.
  --------------------------------------------------------
  p_clk_enable : process (clk) is
  begin

    if rising_edge(clk) then              -- Synchronous process
      if (rst = '1') then                 -- High-active reset
        sig_cnt <= 0;                     -- Clear local counter
        ce      <= '0';                   -- Set output to low

      -- Test number of clock periods
      elsif (sig_cnt >= (g_MAX - 1)) then
        sig_cnt <= 0;                     -- Clear local counter
        ce      <= '1';                   -- Generate clock enable pulse
      else
        sig_cnt <= sig_cnt + 1;
        ce      <= '0';
      end if;
    end if;

  end process p_clk_enable;

end architecture behavioral;

src/driver_7seg_8digits.vhd
library ieee;
  use ieee.std_logic_1164.all;
  use ieee.numeric_std.all;

----------------------------------------------------------

entity driver_7seg_8digits is
  generic (
    g_max : natural := 2 -- 200000
  );
  port (
    clk   : in    std_logic;
    rst   : in    std_logic;
    data1 : in    std_logic_vector(20 downto 0);
    data2 : in    std_logic_vector(20 downto 0);
    data3 : in    std_logic_vector(20 downto 0);
    data4 : in    std_logic_vector(20 downto 0);
    data5 : in    std_logic_vector(20 downto 0);
    data6 : in    std_logic_vector(20 downto 0);
    data7 : in    std_logic_vector(20 downto 0);
    data8 : in    std_logic_vector(20 downto 0);
    seg   : out   std_logic_vector(6 downto 0);
    dig   : out   std_logic_vector(7 downto 0)
  );
end entity driver_7seg_8digits;

----------------------------------------------------------
-- Architecture declaration for display driver
----------------------------------------------------------

architecture behavioral of driver_7seg_8digits is

  -- Internal clock enable
  signal sig_en_2ms : std_logic;

  -- Internal 3-bit counter for multiplexing 8 digits
  signal sig_cnt_3bit : std_logic_vector(2 downto 0);

  -- Internal 8-bit value for 7-segment decoder
  signal sig_hex : std_logic_vector(20 downto 0);

begin

  --------------------------------------------------------
  -- Instance (copy) of clock_enable entity generates
  -- an enable pulse every 4 ms
  --------------------------------------------------------
  clk_en0 : entity work.clock_enable
    generic map (
      g_max => g_max
    )
    port map (
      clk => clk,
      rst => rst,
      ce  => sig_en_2ms
    );

  --------------------------------------------------------
  -- Instance (copy) of cnt_up_down entity performs
  -- a 2-bit down counter
  --------------------------------------------------------
  bin_cnt0 : entity work.cnt_up_down
    generic map (
      g_cnt_width => 3
    )
    port map (
      clk    => clk,
      rst    => rst,
      en     => sig_en_2ms,
      cnt_up => '0',
      cnt    => sig_cnt_3bit

    );

  --------------------------------------------------------
  -- Instance (copy) of hex_7seg entity performs
  -- a 7-segment display decoder
  --------------------------------------------------------
  hex2seg : entity work.hex_7seg
    port map (
      blank => rst,
      hex   => sig_hex,
      seg   => seg
    );

  --------------------------------------------------------
  -- p_mux:
  -- A sequential process that implements a multiplexer for
  -- selecting data for a single digit, a decimal point,
  -- and switches the common anodes of each display.
  --------------------------------------------------------
  p_mux : process (clk) is
  begin

    if (rising_edge(clk)) then
      if (rst = '1') then
        sig_hex <= data1;
        dig     <= "11111110";
      else

        case sig_cnt_3bit is

          when "111" =>

            sig_hex <= data8;
            dig     <= "01111111";

          when "110" =>

            sig_hex <= data7;
            dig     <= "10111111";

          when "101" =>

            sig_hex <= data6;
            dig     <= "11011111";

          when "100" =>

            sig_hex <= data5;
            dig     <= "11101111";

          when "011" =>

            sig_hex <= data4;
            dig     <= "11110111";

          when "010" =>

            sig_hex <= data3;
            dig     <= "11111011";

          when "001" =>

            sig_hex <= data2;
            dig     <= "11111101";

          when others =>

            sig_hex <= data1;
            dig     <= "11111110";

        end case;

      end if;
    end if;

  end process p_mux;

end architecture behavioral;

tb_driver_7seg_8digits.vhd

library ieee;
  use ieee.std_logic_1164.all;

----------------------------------------------------------
-- Entity declaration for testbench
----------------------------------------------------------

entity tb_driver_7seg_8digits is
  -- Entity of testbench is always empty
end entity tb_driver_7seg_8digits;

----------------------------------------------------------
-- Architecture body for testbench
----------------------------------------------------------

architecture testbench of tb_driver_7seg_8digits is

  -- Testbench local constants
  constant c_CLK_100MHZ_PERIOD : time := 10 ns;

  -- Testench local signals
  signal sig_clk_100mhz : std_logic;
  signal sig_rst        : std_logic;
  signal sig_data1      : std_logic_vector(20 downto 0);
  signal sig_data2      : std_logic_vector(20 downto 0);
  signal sig_data3      : std_logic_vector(20 downto 0);
  signal sig_data4      : std_logic_vector(20 downto 0);
  signal sig_data5      : std_logic_vector(20 downto 0);
  signal sig_data6      : std_logic_vector(20 downto 0);
  signal sig_data7      : std_logic_vector(20 downto 0);
  signal sig_data8      : std_logic_vector(20 downto 0);
  signal sig_seg        : std_logic_vector(6 downto 0);
  signal sig_dig        : std_logic_vector(7 downto 0);

begin

  -- Connecting testbench signals with driver_7seg_8digits
  -- entity (Unit Under Test)
  uut_driver_7seg_8digits : entity work.driver_7seg_8digits
    port map (
      clk     => sig_clk_100mhz,
      rst     => sig_rst,
      data1   => sig_data1,
      data2   => sig_data2,
      data3   => sig_data3,
      data4   => sig_data4,
      data5   => sig_data5,
      data6   => sig_data6,
      data7   => sig_data7,
      data8   => sig_data8,
      seg     => sig_seg,
      dig     => sig_dig
    );

  --------------------------------------------------------
  -- Clock generation process
  --------------------------------------------------------
  p_clk_gen : process is
  begin

    while now < 400 ns loop -- 40 periods of 100MHz clock

      sig_clk_100mhz <= '0';
      wait for c_CLK_100MHZ_PERIOD / 2;
      sig_clk_100mhz <= '1';
      wait for c_CLK_100MHZ_PERIOD / 2;

    end loop;
    wait;

  end process p_clk_gen;

  --------------------------------------------------------
  -- Reset generation process
  --------------------------------------------------------
  p_reset_gen : process is
  begin

    sig_rst <= '0';
    wait for 15 ns;
    sig_rst <= '1';
    wait for 70 ns;
    sig_rst <= '0';
    wait;

  end process p_reset_gen;

  --------------------------------------------------------
  -- Data generation process
  --------------------------------------------------------
  p_stimulus : process is
  begin

    report "Stimulus process started";
    sig_data8 <= "000000000001110101110"; -- K
    sig_data7 <= "000000000111011101110"; -- O
    sig_data6 <= "000000000101110111010"; -- P
    sig_data5 <= "000001010111011101110"; -- 3
    sig_data4 <= "000000000000000000000"; -- nothing
    sig_data3 <= "011100011111110000000"; -- -
    sig_data2 <= "000000000101010101110"; -- 4
    sig_data1 <= "000000000000000101110"; -- A

    report "Stimulus process finished";
    wait;

  end process p_stimulus;

end architecture testbench;

sim/driver_7seg_8digits.vcd
$date
  Sat Apr 15 09:03:37 2023
$end
$version
  GHDL v0
$end
$timescale
  1 fs
$end
$scope module standard $end
$upscope $end
$scope module std_logic_1164 $end
$upscope $end
$scope module numeric_std $end
$upscope $end
$scope module tb_driver_7seg_8digits $end
$var reg 1 ! sig_clk_100mhz $end
$var reg 1 " sig_rst $end
$var reg 21 # sig_data1[20:0] $end
$var reg 21 $ sig_data2[20:0] $end
$var reg 21 % sig_data3[20:0] $end
$var reg 21 & sig_data4[20:0] $end
$var reg 21 ' sig_data5[20:0] $end
$var reg 21 ( sig_data6[20:0] $end
$var reg 21 ) sig_data7[20:0] $end
$var reg 21 * sig_data8[20:0] $end
$var reg 7 + sig_seg[6:0] $end
$var reg 8 , sig_dig[7:0] $end
$scope module uut_driver_7seg_8digits $end
$var reg 1 - clk $end
$var reg 1 . rst $end
$var reg 21 / data1[20:0] $end
$var reg 21 0 data2[20:0] $end
$var reg 21 1 data3[20:0] $end
$var reg 21 2 data4[20:0] $end
$var reg 21 3 data5[20:0] $end
$var reg 21 4 data6[20:0] $end
$var reg 21 5 data7[20:0] $end
$var reg 21 6 data8[20:0] $end
$var reg 7 7 seg[6:0] $end
$var reg 8 8 dig[7:0] $end
$var reg 1 9 sig_en_2ms $end
$var reg 3 : sig_cnt_3bit[2:0] $end
$var reg 21 ; sig_hex[20:0] $end
$scope module clk_en0 $end
$var reg 1 < clk $end
$var reg 1 = rst $end
$var reg 1 > ce $end
$var integer 32 ? sig_cnt $end
$upscope $end
$scope module bin_cnt0 $end
$var reg 1 @ clk $end
$var reg 1 A rst $end
$var reg 1 B en $end
$var reg 1 C cnt_up $end
$var reg 3 D cnt[2:0] $end
$var reg 3 E sig_cnt[2:0] $end
$upscope $end
$scope module hex2seg $end
$var reg 1 F blank $end
$var reg 21 G hex[20:0] $end
$var reg 7 H seg[6:0] $end
$upscope $end
$upscope $end
$upscope $end
$enddefinitions $end
#0
0!
0"
b000000000000000101110 #
b000000000101010101110 $
b011100011111110000000 %
b000000000000000000000 &
b000001010111011101110 '
b000000000101110111010 (
b000000000111011101110 )
b000000000001110101110 *
b1111110 +
bUUUUUUUU ,
0-
0.
b000000000000000101110 /
b000000000101010101110 0
b011100011111110000000 1
b000000000000000000000 2
b000001010111011101110 3
b000000000101110111010 4
b000000000111011101110 5
b000000000001110101110 6
b1111110 7
bUUUUUUUU 8
U9
bUUU :
bUUUUUUUUUUUUUUUUUUUUU ;
0<
0=
U>
b0 ?
0@
0A
UB
0C
bUUU D
bUUU E
0F
bUUUUUUUUUUUUUUUUUUUUU G
b1111110 H
#5000000
1!
b0001000 +
b11111110 ,
1-
b0001000 7
b11111110 8
09
b000000000000000101110 ;
1<
0>
b1 ?
1@
0B
b000000000000000101110 G
b0001000 H
#10000000
0!
0-
0<
0@
#15000000
1!
1"
b1111111 +
1-
1.
b1111111 7
b000 :
1<
1=
b0 ?
1@
1A
b000 D
b000 E
1F
b1111111 H
#20000000
0!
0-
0<
0@
#25000000
1!
1-
1<
1@
#30000000
0!
0-
0<
0@
#35000000
1!
1-
1<
1@
#40000000
0!
0-
0<
0@
#45000000
1!
1-
1<
1@
#50000000
0!
0-
0<
0@
#55000000
1!
1-
1<
1@
#60000000
0!
0-
0<
0@
#65000000
1!
1-
1<
1@
#70000000
0!
0-
0<
0@
#75000000
1!
1-
1<
1@
#80000000
0!
0-
0<
0@
#85000000
1!
0"
b0001000 +
1-
0.
b0001000 7
1<
0=
b1 ?
1@
0A
0F
b0001000 H
#90000000
0!
0-
0<
0@
#95000000
1!
1-
19
1<
1>
b0 ?
1@
1B
#100000000
0!
0-
0<
0@
#105000000
1!
1-
09
b111 :
1<
0>
b1 ?
1@
0B
b111 D
b111 E
#110000000
0!
0-
0<
0@
#115000000
1!
b0101000 +
b01111111 ,
1-
b0101000 7
b01111111 8
19
b000000000001110101110 ;
1<
1>
b0 ?
1@
1B
b000000000001110101110 G
b0101000 H
#120000000
0!
0-
0<
0@
#125000000
1!
1-
09
b110 :
1<
0>
b1 ?
1@
0B
b110 D
b110 E
#130000000
0!
0-
0<
0@
#135000000
1!
b1100010 +
b10111111 ,
1-
b1100010 7
b10111111 8
19
b000000000111011101110 ;
1<
1>
b0 ?
1@
1B
b000000000111011101110 G
b1100010 H
#140000000
0!
0-
0<
0@
#145000000
1!
1-
09
b101 :
1<
0>
b1 ?
1@
0B
b101 D
b101 E
#150000000
0!
0-
0<
0@
#155000000
1!
b0011000 +
b11011111 ,
1-
b0011000 7
b11011111 8
19
b000000000101110111010 ;
1<
1>
b0 ?
1@
1B
b000000000101110111010 G
b0011000 H
#160000000
0!
0-
0<
0@
#165000000
1!
1-
09
b100 :
1<
0>
b1 ?
1@
0B
b100 D
b100 E
#170000000
0!
0-
0<
0@
#175000000
1!
b0010010 +
b11101111 ,
1-
b0010010 7
b11101111 8
19
b000001010111011101110 ;
1<
1>
b0 ?
1@
1B
b000001010111011101110 G
b0010010 H
#180000000
0!
0-
0<
0@
#185000000
1!
1-
09
b011 :
1<
0>
b1 ?
1@
0B
b011 D
b011 E
#190000000
0!
0-
0<
0@
#195000000
1!
b1111111 +
b11110111 ,
1-
b1111111 7
b11110111 8
19
b000000000000000000000 ;
1<
1>
b0 ?
1@
1B
b000000000000000000000 G
b1111111 H
#200000000
0!
0-
0<
0@
#205000000
1!
1-
09
b010 :
1<
0>
b1 ?
1@
0B
b010 D
b010 E
#210000000
0!
0-
0<
0@
#215000000
1!
b1111110 +
b11111011 ,
1-
b1111110 7
b11111011 8
19
b011100011111110000000 ;
1<
1>
b0 ?
1@
1B
b011100011111110000000 G
b1111110 H
#220000000
0!
0-
0<
0@
#225000000
1!
1-
09
b001 :
1<
0>
b1 ?
1@
0B
b001 D
b001 E
#230000000
0!
0-
0<
0@
#235000000
1!
b1001100 +
b11111101 ,
1-
b1001100 7
b11111101 8
19
b000000000101010101110 ;
1<
1>
b0 ?
1@
1B
b000000000101010101110 G
b1001100 H
#240000000
0!
0-
0<
0@
#245000000
1!
1-
09
b000 :
1<
0>
b1 ?
1@
0B
b000 D
b000 E
#250000000
0!
0-
0<
0@
#255000000
1!
b0001000 +
b11111110 ,
1-
b0001000 7
b11111110 8
19
b000000000000000101110 ;
1<
1>
b0 ?
1@
1B
b000000000000000101110 G
b0001000 H
#260000000
0!
0-
0<
0@
#265000000
1!
1-
09
b111 :
1<
0>
b1 ?
1@
0B
b111 D
b111 E
#270000000
0!
0-
0<
0@
#275000000
1!
b0101000 +
b01111111 ,
1-
b0101000 7
b01111111 8
19
b000000000001110101110 ;
1<
1>
b0 ?
1@
1B
b000000000001110101110 G
b0101000 H
#280000000
0!
0-
0<
0@
#285000000
1!
1-
09
b110 :
1<
0>
b1 ?
1@
0B
b110 D
b110 E
#290000000
0!
0-
0<
0@
#295000000
1!
b1100010 +
b10111111 ,
1-
b1100010 7
b10111111 8
19
b000000000111011101110 ;
1<
1>
b0 ?
1@
1B
b000000000111011101110 G
b1100010 H
#300000000
0!
0-
0<
0@
#305000000
1!
1-
09
b101 :
1<
0>
b1 ?
1@
0B
b101 D
b101 E
#310000000
0!
0-
0<
0@
#315000000
1!
b0011000 +
b11011111 ,
1-
b0011000 7
b11011111 8
19
b000000000101110111010 ;
1<
1>
b0 ?
1@
1B
b000000000101110111010 G
b0011000 H
#320000000
0!
0-
0<
0@
#325000000
1!
1-
09
b100 :
1<
0>
b1 ?
1@
0B
b100 D
b100 E
#330000000
0!
0-
0<
0@
#335000000
1!
b0010010 +
b11101111 ,
1-
b0010010 7
b11101111 8
19
b000001010111011101110 ;
1<
1>
b0 ?
1@
1B
b000001010111011101110 G
b0010010 H
#340000000
0!
0-
0<
0@
#345000000
1!
1-
09
b011 :
1<
0>
b1 ?
1@
0B
b011 D
b011 E
#350000000
0!
0-
0<
0@
#355000000
1!
b1111111 +
b11110111 ,
1-
b1111111 7
b11110111 8
19
b000000000000000000000 ;
1<
1>
b0 ?
1@
1B
b000000000000000000000 G
b1111111 H
#360000000
0!
0-
0<
0@
#365000000
1!
1-
09
b010 :
1<
0>
b1 ?
1@
0B
b010 D
b010 E
#370000000
0!
0-
0<
0@
#375000000
1!
b1111110 +
b11111011 ,
1-
b1111110 7
b11111011 8
19
b011100011111110000000 ;
1<
1>
b0 ?
1@
1B
b011100011111110000000 G
b1111110 H
#380000000
0!
0-
0<
0@
#385000000
1!
1-
09
b001 :
1<
0>
b1 ?
1@
0B
b001 D
b001 E
#390000000
0!
0-
0<
0@
#395000000
1!
b1001100 +
b11111101 ,
1-
b1001100 7
b11111101 8
19
b000000000101010101110 ;
1<
1>
b0 ?
1@
1B
b000000000101010101110 G
b1001100 H
