src/shifter.vhd
library ieee;
  use ieee.std_logic_1164.all;
  use ieee.numeric_std.all;

entity shifter is
  port (
    sw     : in    std_logic;
    clk    : in    std_logic;
    rst    : in    std_logic;
    input  : in    std_logic;
    output : out   std_logic_vector(20 downto 0)
  );
end entity shifter;

architecture behavioral of shifter is

  signal sig_out  : std_logic_vector(20 downto 0);
  signal sig_cnt  : integer := 0;
  signal zero_cnt : integer := 0;

begin

  p_shifter : process (clk, input) is
  begin

    if rising_edge(clk) then
      if (sw = '0') then
        if (rst = '1') then
          sig_out  <= "000000000000000000000";
          output   <= (others => '0');
          sig_cnt  <= 0;
          zero_cnt <= 0;
        else
          if (input = '0') then
            zero_cnt <= zero_cnt + 1;
          end if;
          if (zero_cnt = 2) then
            output  <= sig_out;
            sig_out <= "000000000000000000000";
            sig_cnt <= 0;
          end if;
          if (input = '1') then
            zero_cnt <= 0;

            sig_out(20) <= sig_out(19);
            sig_out(19) <= sig_out(18);
            sig_out(18) <= sig_out(17);
            sig_out(17) <= sig_out(16);
            sig_out(16) <= sig_out(15);
            sig_out(15) <= sig_out(14);
            sig_out(14) <= sig_out(13);
            sig_out(13) <= sig_out(12);
            sig_out(12) <= sig_out(11);
            sig_out(11) <= sig_out(10);
            sig_out(10) <= sig_out(9);
            sig_out(9)  <= sig_out(8);
            sig_out(8)  <= sig_out(7);
            sig_out(7)  <= sig_out(6);
            sig_out(6)  <= sig_out(5);
            sig_out(5)  <= sig_out(4);
            sig_out(4)  <= sig_out(3);
            sig_out(3)  <= sig_out(2);
            sig_out(2)  <= sig_out(1);
            sig_out(1)  <= sig_out(0);
            sig_out(0)  <= input;
            sig_cnt     <= sig_cnt + 1;
            if (sig_cnt = 20) then
              output  <= sig_out;
              sig_out <= "000000000000000000000";
              sig_cnt <= 0;
            end if;
          end if;
          if (zero_cnt < 1) then
            sig_out(20) <= sig_out(19);
            sig_out(19) <= sig_out(18);
            sig_out(18) <= sig_out(17);
            sig_out(17) <= sig_out(16);
            sig_out(16) <= sig_out(15);
            sig_out(15) <= sig_out(14);
            sig_out(14) <= sig_out(13);
            sig_out(13) <= sig_out(12);
            sig_out(12) <= sig_out(11);
            sig_out(11) <= sig_out(10);
            sig_out(10) <= sig_out(9);
            sig_out(9)  <= sig_out(8);
            sig_out(8)  <= sig_out(7);
            sig_out(7)  <= sig_out(6);
            sig_out(6)  <= sig_out(5);
            sig_out(5)  <= sig_out(4);
            sig_out(4)  <= sig_out(3);
            sig_out(3)  <= sig_out(2);
            sig_out(2)  <= sig_out(1);
            sig_out(1)  <= sig_out(0);
            sig_out(0)  <= input;
            sig_cnt     <= sig_cnt + 1;
            if (sig_cnt = 20) then
              output  <= sig_out;
              sig_out <= "000000000000000000000";
              sig_cnt <= 0;
            end if;
          end if;
        end if;
      else
        sig_out  <= "000000000000000000000";
        output   <= (others => '0');
        sig_cnt  <= 0;
        zero_cnt <= 0;
      end if;
    end if;

  end process p_shifter;

end architecture behavioral;

tb/tb_shifter.vhd
library ieee;
  use ieee.std_logic_1164.all;
  use ieee.numeric_std.all;

entity tb_shifter is
--  Port ( );
end entity tb_shifter;

architecture testbench of tb_shifter is

  constant c_clk_100mhz_period : time := 10 ns;

  signal sw             : std_logic;
  signal rst            : std_logic;
  signal sig_clk_100mhz : std_logic;
  signal input          : std_logic;
  signal output         : std_logic_vector(20 downto 0);

begin

  uut_shifter : entity work.shifter
    port map (
      sw     => sw,
      rst    => rst,
      clk    => sig_clk_100mhz,
      input  => input,
      output => output
    );

  p_clk_gen : process is
  begin

    while now < 2000 ns loop -- 200 periods of 100MHz clock

      sig_clk_100mhz <= '0';
      wait for c_clk_100mhz_period / 2;
      sig_clk_100mhz <= '1';
      wait for c_clk_100mhz_period / 2;

    end loop;

    wait;

  end process p_clk_gen;

  p_reset_gen : process is
  begin

    rst <= '0';
    wait for 10 ns;
    rst <= '1';
    wait for 90 ns;
    rst <= '0';
    wait for 1500 ns;
    rst <= '1';
    wait for 90 ns;
    rst <= '0';
    wait;

  end process p_reset_gen;

  p_sw : process is
  begin

    sw <= '0';
    wait;

  end process p_sw;

  p_stimulus : process is
  begin

    input <= '0';
    wait for 200 ns; -- NO INPUT
    input <= '1';
    wait for 10 ns;
    input <= '0';
    wait for 10 ns;  -- A
    input <= '1';
    wait for 30 ns;
    input <= '0';
    wait for 30 ns;  -- Pause
    input <= '1';
    wait for 30 ns;
    input <= '0';
    wait for 10 ns;
    input <= '1';
    wait for 10 ns;
    input <= '0';
    wait for 10 ns;  -- B
    input <= '1';
    wait for 10 ns;
    input <= '0';
    wait for 10 ns;
    input <= '1';
    wait for 10 ns;
    input <= '0';
    wait for 30 ns;  -- Pause
    input <= '1';
    wait for 30 ns;
    input <= '0';
    wait for 10 ns;
    input <= '1';
    wait for 10 ns;
    input <= '0';
    wait for 10 ns;  -- C
    input <= '1';
    wait for 30 ns;
    input <= '0';
    wait for 10 ns;
    input <= '1';
    wait for 10 ns;
    input <= '0';
    wait for 30 ns;  -- Pause
    input <= '1';
    wait for 10 ns;
    input <= '0';
    wait for 10 ns;
    input <= '1';
    wait for 30 ns;
    input <= '0';
    wait for 10 ns;  -- J
    input <= '1';
    wait for 30 ns;
    input <= '0';
    wait for 10 ns;
    input <= '1';
    wait for 30 ns;
    input <= '0';
    wait for 30 ns;  -- Pause
    input <= '1';
    wait for 30 ns;
    input <= '0';
    wait for 10 ns;
    input <= '1';
    wait for 30 ns;  -- O
    input <= '0';
    wait for 10 ns;
    input <= '1';
    wait for 30 ns;
    input <= '0';
    wait for 30 ns;  -- Pause
    input <= '1';
    wait for 30 ns;
    input <= '0';
    wait for 10 ns;
    input <= '1';
    wait for 30 ns;  -- 0
    input <= '0';
    wait for 10 ns;
    input <= '1';
    wait for 30 ns;
    input <= '0';
    wait for 10 ns;
    input <= '1';
    wait for 30 ns;
    input <= '0';
    wait for 10 ns;
    input <= '1';
    wait for 30 ns;
    input <= '0';
    wait for 70 ns;  -- Pause
    wait;

  end process p_stimulus;

end architecture testbench;

sim/shifter.vcd
$date
  Sat Apr 22 10:26:58 2023
$end
$version
  GHDL v0
$end
$timescale
  1 fs
$end
$scope module standard $end
$upscope $end
$scope module std_logic_1164 $end
$upscope $end
$scope module numeric_std $end
$upscope $end
$scope module tb_shifter $end
$var reg 1 ! sw $end
$var reg 1 " rst $end
$var reg 1 # sig_clk_100mhz $end
$var reg 1 $ input $end
$var reg 21 % output[20:0] $end
$scope module uut_shifter $end
$var reg 1 & sw $end
$var reg 1 ' clk $end
$var reg 1 ( rst $end
$var reg 1 ) input $end
$var reg 21 * output[20:0] $end
$var reg 21 + sig_out[20:0] $end
$var integer 32 , sig_cnt $end
$var integer 32 - zero_cnt $end
$upscope $end
$upscope $end
$enddefinitions $end
#0
0!
0"
0#
0$
bUUUUUUUUUUUUUUUUUUUUU %
0&
0'
0(
0)
bUUUUUUUUUUUUUUUUUUUUU *
bUUUUUUUUUUUUUUUUUUUUU +
b0 ,
b0 -
#5000000
1#
1'
bUUUUUUUUUUUUUUUUUUUU0 +
b1 ,
b1 -
#10000000
1"
0#
0'
1(
#15000000
1#
b000000000000000000000 %
1'
b000000000000000000000 *
b000000000000000000000 +
b0 ,
b0 -
#20000000
0#
0'
#25000000
1#
1'
#30000000
0#
0'
#35000000
1#
1'
#40000000
0#
0'
#45000000
1#
1'
#50000000
0#
0'
#55000000
1#
1'
#60000000
0#
0'
#65000000
1#
1'
#70000000
0#
0'
#75000000
1#
1'
#80000000
0#
0'
#85000000
1#
1'
#90000000
0#
0'
#95000000
1#
1'
#100000000
0"
0#
0'
0(
#105000000
1#
1'
b1 ,
b1 -
#110000000
0#
0'
#115000000
1#
1'
b10 -
#120000000
0#
0'
#125000000
1#
1'
b0 ,
b11 -
#130000000
0#
0'
#135000000
1#
1'
b100 -
#140000000
0#
0'
#145000000
1#
1'
b101 -
#150000000
0#
0'
#155000000
1#
1'
b110 -
#160000000
0#
0'
#165000000
1#
1'
b111 -
#170000000
0#
0'
#175000000
1#
1'
b1000 -
#180000000
0#
0'
#185000000
1#
1'
b1001 -
#190000000
0#
0'
#195000000
1#
1'
b1010 -
#200000000
0#
1$
0'
1)
#205000000
1#
1'
b000000000000000000001 +
b1 ,
b0 -
#210000000
0#
0$
0'
0)
#215000000
1#
1'
b000000000000000000010 +
b10 ,
b1 -
#220000000
0#
1$
0'
1)
#225000000
1#
1'
b000000000000000000101 +
b11 ,
b0 -
#230000000
0#
0'
#235000000
1#
1'
b000000000000000001011 +
b100 ,
#240000000
0#
0'
#245000000
1#
1'
b000000000000000010111 +
b101 ,
#250000000
0#
0$
0'
0)
#255000000
1#
1'
b000000000000000101110 +
b110 ,
b1 -
#260000000
0#
0'
#265000000
1#
1'
b10 -
#270000000
0#
0'
#275000000
1#
b000000000000000101110 %
1'
b000000000000000101110 *
b000000000000000000000 +
b0 ,
b11 -
#280000000
0#
1$
0'
1)
#285000000
1#
1'
b000000000000000000001 +
b1 ,
b0 -
#290000000
0#
0'
#295000000
1#
1'
b000000000000000000011 +
b10 ,
#300000000
0#
0'
#305000000
1#
1'
b000000000000000000111 +
b11 ,
#310000000
0#
0$
0'
0)
#315000000
1#
1'
b000000000000000001110 +
b100 ,
b1 -
#320000000
0#
1$
0'
1)
#325000000
1#
1'
b000000000000000011101 +
b101 ,
b0 -
#330000000
0#
0$
0'
0)
#335000000
1#
1'
b000000000000000111010 +
b110 ,
b1 -
#340000000
0#
1$
0'
1)
#345000000
1#
1'
b000000000000001110101 +
b111 ,
b0 -
#350000000
0#
0$
0'
0)
#355000000
1#
1'
b000000000000011101010 +
b1000 ,
b1 -
#360000000
0#
1$
0'
1)
#365000000
1#
1'
b000000000000111010101 +
b1001 ,
b0 -
#370000000
0#
0$
0'
0)
#375000000
1#
1'
b000000000001110101010 +
b1010 ,
b1 -
#380000000
0#
0'
#385000000
1#
1'
b10 -
#390000000
0#
0'
#395000000
1#
b000000000001110101010 %
1'
b000000000001110101010 *
b000000000000000000000 +
b0 ,
b11 -
#400000000
0#
1$
0'
1)
#405000000
1#
1'
b000000000000000000001 +
b1 ,
b0 -
#410000000
0#
0'
#415000000
1#
1'
b000000000000000000011 +
b10 ,
#420000000
0#
0'
#425000000
1#
1'
b000000000000000000111 +
b11 ,
#430000000
0#
0$
0'
0)
#435000000
1#
1'
b000000000000000001110 +
b100 ,
b1 -
#440000000
0#
1$
0'
1)
#445000000
1#
1'
b000000000000000011101 +
b101 ,
b0 -
#450000000
0#
0$
0'
0)
#455000000
1#
1'
b000000000000000111010 +
b110 ,
b1 -
#460000000
0#
1$
0'
1)
#465000000
1#
1'
b000000000000001110101 +
b111 ,
b0 -
#470000000
0#
0'
#475000000
1#
1'
b000000000000011101011 +
b1000 ,
#480000000
0#
0'
#485000000
1#
1'
b000000000000111010111 +
b1001 ,
#490000000
0#
0$
0'
0)
#495000000
1#
1'
b000000000001110101110 +
b1010 ,
b1 -
#500000000
0#
1$
0'
1)
#505000000
1#
1'
b000000000011101011101 +
b1011 ,
b0 -
#510000000
0#
0$
0'
0)
#515000000
1#
1'
b000000000111010111010 +
b1100 ,
b1 -
#520000000
0#
0'
#525000000
1#
1'
b10 -
#530000000
0#
0'
#535000000
1#
b000000000111010111010 %
1'
b000000000111010111010 *
b000000000000000000000 +
b0 ,
b11 -
#540000000
0#
1$
0'
1)
#545000000
1#
1'
b000000000000000000001 +
b1 ,
b0 -
#550000000
0#
0$
0'
0)
#555000000
1#
1'
b000000000000000000010 +
b10 ,
b1 -
#560000000
0#
1$
0'
1)
#565000000
1#
1'
b000000000000000000101 +
b11 ,
b0 -
#570000000
0#
0'
#575000000
1#
1'
b000000000000000001011 +
b100 ,
#580000000
0#
0'
#585000000
1#
1'
b000000000000000010111 +
b101 ,
#590000000
0#
0$
0'
0)
#595000000
1#
1'
b000000000000000101110 +
b110 ,
b1 -
#600000000
0#
1$
0'
1)
#605000000
1#
1'
b000000000000001011101 +
b111 ,
b0 -
#610000000
0#
0'
#615000000
1#
1'
b000000000000010111011 +
b1000 ,
#620000000
0#
0'
#625000000
1#
1'
b000000000000101110111 +
b1001 ,
#630000000
0#
0$
0'
0)
#635000000
1#
1'
b000000000001011101110 +
b1010 ,
b1 -
#640000000
0#
1$
0'
1)
#645000000
1#
1'
b000000000010111011101 +
b1011 ,
b0 -
#650000000
0#
0'
#655000000
1#
1'
b000000000101110111011 +
b1100 ,
#660000000
0#
0'
#665000000
1#
1'
b000000001011101110111 +
b1101 ,
#670000000
0#
0$
0'
0)
#675000000
1#
1'
b000000010111011101110 +
b1110 ,
b1 -
#680000000
0#
0'
#685000000
1#
1'
b10 -
#690000000
0#
0'
#695000000
1#
b000000010111011101110 %
1'
b000000010111011101110 *
b000000000000000000000 +
b0 ,
b11 -
#700000000
0#
1$
0'
1)
#705000000
1#
1'
b000000000000000000001 +
b1 ,
b0 -
#710000000
0#
0'
#715000000
1#
1'
b000000000000000000011 +
b10 ,
#720000000
0#
0'
#725000000
1#
1'
b000000000000000000111 +
b11 ,
#730000000
0#
0$
0'
0)
#735000000
1#
1'
b000000000000000001110 +
b100 ,
b1 -
#740000000
0#
1$
0'
1)
#745000000
1#
1'
b000000000000000011101 +
b101 ,
b0 -
#750000000
0#
0'
#755000000
1#
1'
b000000000000000111011 +
b110 ,
#760000000
0#
0'
#765000000
1#
1'
b000000000000001110111 +
b111 ,
#770000000
0#
0$
0'
0)
#775000000
1#
1'
b000000000000011101110 +
b1000 ,
b1 -
#780000000
0#
1$
0'
1)
#785000000
1#
1'
b000000000000111011101 +
b1001 ,
b0 -
#790000000
0#
0'
#795000000
1#
1'
b000000000001110111011 +
b1010 ,
#800000000
0#
0'
#805000000
1#
1'
b000000000011101110111 +
b1011 ,
#810000000
0#
0$
0'
0)
#815000000
1#
1'
b000000000111011101110 +
b1100 ,
b1 -
#820000000
0#
0'
#825000000
1#
1'
b10 -
#830000000
0#
0'
#835000000
1#
b000000000111011101110 %
1'
b000000000111011101110 *
b000000000000000000000 +
b0 ,
b11 -
#840000000
0#
1$
0'
1)
#845000000
1#
1'
b000000000000000000001 +
b1 ,
b0 -
#850000000
0#
0'
#855000000
1#
1'
b000000000000000000011 +
b10 ,
#860000000
0#
0'
#865000000
1#
1'
b000000000000000000111 +
b11 ,
#870000000
0#
0$
0'
0)
#875000000
1#
1'
b000000000000000001110 +
b100 ,
b1 -
#880000000
0#
1$
0'
1)
#885000000
1#
1'
b000000000000000011101 +
b101 ,
b0 -
#890000000
0#
0'
#895000000
1#
1'
b000000000000000111011 +
b110 ,
#900000000
0#
0'
#905000000
1#
1'
b000000000000001110111 +
b111 ,
#910000000
0#
0$
0'
0)
#915000000
1#
1'
b000000000000011101110 +
b1000 ,
b1 -
#920000000
0#
1$
0'
1)
#925000000
1#
1'
b000000000000111011101 +
b1001 ,
b0 -
#930000000
0#
0'
#935000000
1#
1'
b000000000001110111011 +
b1010 ,
#940000000
0#
0'
#945000000
1#
1'
b000000000011101110111 +
b1011 ,
#950000000
0#
0$
0'
0)
#955000000
1#
1'
b000000000111011101110 +
b1100 ,
b1 -
#960000000
0#
1$
0'
1)
#965000000
1#
1'
b000000001110111011101 +
b1101 ,
b0 -
#970000000
0#
0'
#975000000
1#
1'
b000000011101110111011 +
b1110 ,
#980000000
0#
0'
#985000000
1#
1'
b000000111011101110111 +
b1111 ,
#990000000
0#
0$
0'
0)
#995000000
1#
1'
b000001110111011101110 +
b10000 ,
b1 -
#1000000000
0#
1$
0'
1)
#1005000000
1#
1'
b000011101110111011101 +
b10001 ,
b0 -
#1010000000
0#
0'
#1015000000
1#
1'
b000111011101110111011 +
b10010 ,
#1020000000
0#
0'
#1025000000
1#
1'
b001110111011101110111 +
b10011 ,
#1030000000
0#
0$
0'
0)
#1035000000
1#
1'
b011101110111011101110 +
b10100 ,
b1 -
#1040000000
0#
0'
#1045000000
1#
1'
b10 -
#1050000000
0#
0'
#1055000000
1#
b011101110111011101110 %
1'
b011101110111011101110 *
b000000000000000000000 +
b0 ,
b11 -
#1060000000
0#
0'
#1065000000
1#
1'
b100 -
#1070000000
0#
0'
#1075000000
1#
1'
b101 -
#1080000000
0#
0'
#1085000000
1#
1'
b110 -
#1090000000
0#
0'
#1095000000
1#
1'
b111 -
#1100000000
0#
0'
#1105000000
1#
1'
b1000 -
#1110000000
0#
0'
#1115000000
1#
1'
b1001 -
#1120000000
0#
0'
#1125000000
1#
1'
b1010 -
#1130000000
0#
0'
#1135000000
1#
1'
b1011 -
#1140000000
0#
0'
#1145000000
1#
1'
b1100 -
#1150000000
0#
0'
#1155000000
1#
1'
b1101 -
#1160000000
0#
0'
#1165000000
1#
1'
b1110 -
#1170000000
0#
0'
#1175000000
1#
1'
b1111 -
#1180000000
0#
0'
#1185000000
1#
1'
b10000 -
#1190000000
0#
0'
#1195000000
1#
1'
b10001 -
#1200000000
0#
0'
#1205000000
1#
1'
b10010 -
#1210000000
0#
0'
#1215000000
1#
1'
b10011 -
#1220000000
0#
0'
#1225000000
1#
1'
b10100 -
#1230000000
0#
0'
#1235000000
1#
1'
b10101 -
#1240000000
0#
0'
#1245000000
1#
1'
b10110 -
#1250000000
0#
0'
#1255000000
1#
1'
b10111 -
#1260000000
0#
0'
#1265000000
1#
1'
b11000 -
#1270000000
0#
0'
#1275000000
1#
1'
b11001 -
#1280000000
0#
0'
#1285000000
1#
1'
b11010 -
#1290000000
0#
0'
#1295000000
1#
1'
b11011 -
#1300000000
0#
0'
#1305000000
1#
1'
b11100 -
#1310000000
0#
0'
#1315000000
1#
1'
b11101 -
#1320000000
0#
0'
#1325000000
1#
1'
b11110 -
#1330000000
0#
0'
#1335000000
1#
1'
b11111 -
#1340000000
0#
0'
#1345000000
1#
1'
b100000 -
#1350000000
0#
0'
#1355000000
1#
1'
b100001 -
#1360000000
0#
0'
#1365000000
1#
1'
b100010 -
#1370000000
0#
0'
#1375000000
1#
1'
b100011 -
#1380000000
0#
0'
#1385000000
1#
1'
b100100 -
#1390000000
0#
0'
#1395000000
1#
1'
b100101 -
#1400000000
0#
0'
#1405000000
1#
1'
b100110 -
#1410000000
0#
0'
#1415000000
1#
1'
b100111 -
#1420000000
0#
0'
#1425000000
1#
1'
b101000 -
#1430000000
0#
0'
#1435000000
1#
1'
b101001 -
#1440000000
0#
0'
#1445000000
1#
1'
b101010 -
#1450000000
0#
0'
#1455000000
1#
1'
b101011 -
#1460000000
0#
0'
#1465000000
1#
1'
b101100 -
#1470000000
0#
0'
#1475000000
1#
1'
b101101 -
#1480000000
0#
0'
#1485000000
1#
1'
b101110 -
#1490000000
0#
0'
#1495000000
1#
1'
b101111 -
#1500000000
0#
0'
#1505000000
1#
1'
b110000 -
#1510000000
0#
0'
#1515000000
1#
1'
b110001 -
#1520000000
0#
0'
#1525000000
1#
1'
b110010 -
#1530000000
0#
0'
#1535000000
1#
1'
b110011 -
#1540000000
0#
0'
#1545000000
1#
1'
b110100 -
#1550000000
0#
0'
#1555000000
1#
1'
b110101 -
#1560000000
0#
0'
#1565000000
1#
1'
b110110 -
#1570000000
0#
0'
#1575000000
1#
1'
b110111 -
#1580000000
0#
0'
#1585000000
1#
1'
b111000 -
#1590000000
0#
0'
#1595000000
1#
1'
b111001 -
#1600000000
1"
0#
0'
1(
#1605000000
1#
b000000000000000000000 %
1'
b000000000000000000000 *
b0 -
#1610000000
0#
0'
#1615000000
1#
1'
#1620000000
0#
0'
#1625000000
1#
1'
#1630000000
0#
0'
#1635000000
1#
1'
#1640000000
0#
0'
#1645000000
1#
1'
#1650000000
0#
0'
#1655000000
1#
1'
#1660000000
0#
0'
#1665000000
1#
1'
#1670000000
0#
0'
#1675000000
1#
1'
#1680000000
0#
0'
#1685000000
1#
1'
#1690000000
0"
0#
0'
0(
#1695000000
1#
1'
b1 ,
b1 -
#1700000000
0#
0'
#1705000000
1#
1'
b10 -
#1710000000
0#
0'
#1715000000
1#
1'
b0 ,
b11 -
#1720000000
0#
0'
#1725000000
1#
1'
b100 -
#1730000000
0#
0'
#1735000000
1#
1'
b101 -
#1740000000
0#
0'
#1745000000
1#
1'
b110 -
#1750000000
0#
0'
#1755000000
1#
1'
b111 -
#1760000000
0#
0'
#1765000000
1#
1'
b1000 -
#1770000000
0#
0'
#1775000000
1#
1'
b1001 -
#1780000000
0#
0'
#1785000000
1#
1'
b1010 -
#1790000000
0#
0'
#1795000000
1#
1'
b1011 -
#1800000000
0#
0'
#1805000000
1#
1'
b1100 -
#1810000000
0#
0'
#1815000000
1#
1'
b1101 -
#1820000000
0#
0'
#1825000000
1#
1'
b1110 -
#1830000000
0#
0'
#1835000000
1#
1'
b1111 -
#1840000000
0#
0'
#1845000000
1#
1'
b10000 -
#1850000000
0#
0'
#1855000000
1#
1'
b10001 -
#1860000000
0#
0'
#1865000000
1#
1'
b10010 -
#1870000000
0#
0'
#1875000000
1#
1'
b10011 -
#1880000000
0#
0'
#1885000000
1#
1'
b10100 -
#1890000000
0#
0'
#1895000000
1#
1'
b10101 -
#1900000000
0#
0'
#1905000000
1#
1'
b10110 -
#1910000000
0#
0'
#1915000000
1#
1'
b10111 -
#1920000000
0#
0'
#1925000000
1#
1'
b11000 -
#1930000000
0#
0'
#1935000000
1#
1'
b11001 -
#1940000000
0#
0'
#1945000000
1#
1'
b11010 -
#1950000000
0#
0'
#1955000000
1#
1'
b11011 -
#1960000000
0#
0'
#1965000000
1#
1'
b11100 -
#1970000000
0#
0'
#1975000000
1#
1'
b11101 -
#1980000000
0#
0'
#1985000000
1#
1'
b11110 -
#1990000000
0#
0'
#1995000000
1#
1'
b11111 -
