src/signal_sender.vhd
library ieee;
  use ieee.std_logic_1164.all;
  use ieee.numeric_std.all;

entity signal_sender is
  port (
    clk     : in    std_logic;
    rst     : in    std_logic;
    send    : in    std_logic;
    data1   : in    std_logic_vector(20 downto 0);
    data2   : in    std_logic_vector(20 downto 0);
    data3   : in    std_logic_vector(20 downto 0);
    data4   : in    std_logic_vector(20 downto 0);
    data5   : in    std_logic_vector(20 downto 0);
    data6   : in    std_logic_vector(20 downto 0);
    data7   : in    std_logic_vector(20 downto 0);
    data8   : in    std_logic_vector(20 downto 0);
    output  : out   std_logic;
    led16_r : out   std_logic;
    led16_g : out   std_logic;
    led16_b : out   std_logic
  );
end entity signal_sender;

architecture behavioral of signal_sender is

  signal index     : integer range 0 to 20 := 20;
  signal data_cnt  : integer range 0 to 8  := 7;
  signal one_start : integer range 0 to 20 := 20;
  signal cnt       : integer range 0 to 1  := 0;

begin

  p_signal_sender : process (clk, send) is
  begin

    if rising_edge(clk) then
      if (rst = '1') then
        output    <= '0';
        led16_r   <= '0';
        led16_g   <= '0';
        led16_b   <= '0';
        index     <= 20;
        data_cnt  <= 7;
        one_start <= 20;
        cnt       <= 0;
      elsif (send = '1') then
        if (data_cnt = 0) then
          if (index = 20) then

            for i in 0 to 20 loop

              if (data1(i) = '1') then
                one_start <= i;
                cnt       <= cnt + 1;
              end if;

            end loop;

          end if;
          if (cnt = 1) then
            index <= one_start;
            cnt   <= 0;
          else
            output <= data1(index);
            index  <= (index - 1) mod 21;
          end if;
        end if;
        if (data_cnt = 1) then
          led16_r <= '1';
          led16_g <= '0';
          led16_b <= '0';
          if (index = 20) then

            for i in 0 to 20 loop

              if (data2(i) = '1') then
                one_start <= i;
                cnt       <= cnt + 1;
              end if;

            end loop;

          end if;
          if (cnt = 1) then
            index <= one_start;
            cnt   <= 0;
          else
            output <= data2(index);
            index  <= (index - 1) mod 21;
          end if;
        end if;
        if (data_cnt = 2) then
          led16_r <= '1';
          led16_g <= '0';
          led16_b <= '0';
          if (index = 20) then

            for i in 0 to 20 loop

              if (data3(i) = '1') then
                one_start <= i;
                cnt       <= cnt + 1;
              end if;

            end loop;

          end if;
          if (cnt = 1) then
            index <= one_start;
            cnt   <= 0;
          else
            output <= data3(index);
            index  <= (index - 1) mod 21;
          end if;
        end if;
        if (data_cnt = 3) then
          led16_r <= '1';
          led16_g <= '0';
          led16_b <= '0';
          if (index = 20) then

            for i in 0 to 20 loop

              if (data4(i) = '1') then
                one_start <= i;
                cnt       <= cnt + 1;
              end if;

            end loop;

          end if;
          if (cnt = 1) then
            index <= one_start;
            cnt   <= 0;
          else
            output <= data4(index);
            index  <= (index - 1) mod 21;
          end if;
        end if;
        if (data_cnt = 4) then
          led16_r <= '1';
          led16_g <= '0';
          led16_b <= '0';
          if (index = 20) then

            for i in 0 to 20 loop

              if (data5(i) = '1') then
                one_start <= i;
                cnt       <= cnt + 1;
              end if;

            end loop;

          end if;
          if (cnt = 1) then
            index <= one_start;
            cnt   <= 0;
          else
            output <= data5(index);
            index  <= (index - 1) mod 21;
          end if;
        end if;
        if (data_cnt = 5) then
          led16_r <= '1';
          led16_g <= '0';
          led16_b <= '0';
          if (index = 20) then

            for i in 0 to 20 loop

              if (data6(i) = '1') then
                one_start <= i;
                cnt       <= cnt + 1;
              end if;

            end loop;

          end if;
          if (cnt = 1) then
            index <= one_start;
            cnt   <= 0;
          else
            output <= data6(index);
            index  <= (index - 1) mod 21;
          end if;
        end if;
        if (data_cnt = 6) then
          led16_r <= '1';
          led16_g <= '0';
          led16_b <= '0';
          if (index = 20) then

            for i in 0 to 20 loop

              if (data7(i) = '1') then
                one_start <= i;
                cnt       <= cnt + 1;
              end if;

            end loop;

          end if;

          if (cnt = 1) then
            index <= one_start;
            cnt   <= 0;
          else
            output <= data7(index);
            index  <= (index - 1) mod 21;
          end if;
        end if;
        if (data_cnt = 7) then
          led16_r <= '1';
          led16_g <= '0';
          led16_b <= '0';
          if (index = 20) then

            for i in 0 to 20 loop

              if (data8(i) = '1') then
                one_start <= i;
                cnt       <= cnt + 1;
              end if;

            end loop;

          end if;
          if (cnt = 1) then
            index <= one_start;
            cnt   <= 0;
          else
            output <= data8(index);
            index  <= (index - 1) mod 21;
          end if;
        end if;
        if (data_cnt = 8) then
          output  <= '0';
          index   <= 1;
          led16_r <= '0';
          led16_g <= '1';
          led16_b <= '0';
        end if;
        if (index = 0) then
          data_cnt <= (data_cnt - 1) mod 9;
          cnt      <= 0;
        end if;
      else
        index     <= 20;
        data_cnt  <= 7;
        one_start <= 20;
        cnt       <= 0;
        led16_r   <= '0';
        led16_g   <= '0';
        led16_b   <= '0';
        output    <= '0';
      end if;
    end if;

  end process p_signal_sender;

end architecture behavioral;

proj/tb_signal_sender.vhd
library ieee;
  use ieee.std_logic_1164.all;
  use ieee.numeric_std.all;


entity tb_signal_sender is
--  Port ( );
end tb_signal_sender;

architecture testbench of tb_signal_sender is

    constant c_CLK_100MHZ_PERIOD : time := 10 ns;

    signal rst               : std_logic;
    signal sig_clk_100mhz    : std_logic;
    signal send       : std_logic;
    signal data1      : std_logic_vector(20 downto 0);
    signal data2      : std_logic_vector(20 downto 0);
    signal data3      : std_logic_vector(20 downto 0);
    signal data4      : std_logic_vector(20 downto 0);
    signal data5      : std_logic_vector(20 downto 0);
    signal data6      : std_logic_vector(20 downto 0);
    signal data7      : std_logic_vector(20 downto 0);
    signal data8      : std_logic_vector(20 downto 0);
    signal output     : std_logic;
    signal LED16_R    : std_logic;
    signal LED16_G    : std_logic;
    signal LED16_B    : std_logic;


begin
    uut_signal_sender: entity work.signal_sender
        port map(
            rst        => rst,
            clk        => sig_clk_100mhz,
            send       => send,
            data1      => data1,
            data2      => data2,
            data3      => data3,
            data4      => data4,
            data5      => data5,
            data6      => data6,
            data7      => data7,
            data8      => data8,
            output     => output,
            LED16_R    => LED16_R,
            LED16_G    => LED16_G,
            LED16_B    => LED16_B
        );
        
    p_clk_gen : process is
    begin
          
        while now < 2800 ns loop -- 200 periods of 100MHz clock
          
             sig_clk_100mhz <= '0';
             wait for c_CLK_100MHZ_PERIOD / 2;
             sig_clk_100mhz <= '1';
             wait for c_CLK_100MHZ_PERIOD / 2;
          
        end loop;
        wait;
          
    end process p_clk_gen;

    p_reset_gen : process is
    begin
      
        rst <= '0';
        wait for 10 ns;
        rst <= '1';
        wait for 90 ns;
        rst <= '0';
        wait for 10 ns;
        wait;
      
    end process p_reset_gen;


    p_stimulus : process
    begin 
        data1 <= "000000000000000001110";
        data2 <= "000000000000010101110";
        data3 <= "000000000000010101110";
        data4 <= "000000000000000101110";
        data5 <= "000000000001011101010";
        data6 <= "000000000111011101110";
        data7 <= "011101110111011101110";
        data8 <= "011101110111011101110";
        send <= '0';
        wait for 200 ns;
        send <= '1';
        wait for 1200 ns;
        send <= '0';
        wait for 200 ns;
        send <= '1';
        wait for 1200 ns;
        send <= '0';
        wait;
    end process p_stimulus;
end architecture testbench;

sim/signal_sender.vcd
$date
  Sat Apr 15 08:49:26 2023
$end
$version
  GHDL v0
$end
$timescale
  1 fs
$end
$scope module standard $end
$upscope $end
$scope module std_logic_1164 $end
$upscope $end
$scope module numeric_std $end
$upscope $end
$scope module tb_signal_sender $end
$var reg 1 ! rst $end
$var reg 1 " sig_clk_100mhz $end
$var reg 1 # send $end
$var reg 21 $ data1[20:0] $end
$var reg 21 % data2[20:0] $end
$var reg 21 & data3[20:0] $end
$var reg 21 ' data4[20:0] $end
$var reg 21 ( data5[20:0] $end
$var reg 21 ) data6[20:0] $end
$var reg 21 * data7[20:0] $end
$var reg 21 + data8[20:0] $end
$var reg 1 , output $end
$var reg 1 - led16_r $end
$var reg 1 . led16_g $end
$var reg 1 / led16_b $end
$scope module uut_signal_sender $end
$var reg 1 0 clk $end
$var reg 1 1 rst $end
$var reg 1 2 send $end
$var reg 21 3 data1[20:0] $end
$var reg 21 4 data2[20:0] $end
$var reg 21 5 data3[20:0] $end
$var reg 21 6 data4[20:0] $end
$var reg 21 7 data5[20:0] $end
$var reg 21 8 data6[20:0] $end
$var reg 21 9 data7[20:0] $end
$var reg 21 : data8[20:0] $end
$var reg 1 ; output $end
$var reg 1 < led16_r $end
$var reg 1 = led16_g $end
$var reg 1 > led16_b $end
$var integer 32 ? index $end
$var integer 32 @ data_cnt $end
$var integer 32 A one_start $end
$var integer 32 B cnt $end
$upscope $end
$upscope $end
$enddefinitions $end
#0
0!
0"
0#
b000000000000000001110 $
b000000000000010101110 %
b000000000000010101110 &
b000000000000000101110 '
b000000000001011101010 (
b000000000111011101110 )
b011101110111011101110 *
b011101110111011101110 +
U,
0-
0.
0/
00
01
02
b000000000000000001110 3
b000000000000010101110 4
b000000000000010101110 5
b000000000000000101110 6
b000000000001011101010 7
b000000000111011101110 8
b011101110111011101110 9
b011101110111011101110 :
U;
0<
0=
0>
b10100 ?
b111 @
b10100 A
b0 B
#5000000
1"
10
#10000000
1!
0"
0,
00
11
0;
#15000000
1"
10
#20000000
0"
00
#25000000
1"
10
#30000000
0"
00
#35000000
1"
10
#40000000
0"
00
#45000000
1"
10
#50000000
0"
00
#55000000
1"
10
#60000000
0"
00
#65000000
1"
10
#70000000
0"
00
#75000000
1"
10
#80000000
0"
00
#85000000
1"
10
#90000000
0"
00
#95000000
1"
10
#100000000
0!
0"
00
01
#105000000
1"
10
#110000000
0"
00
#115000000
1"
10
#120000000
0"
00
#125000000
1"
10
#130000000
0"
00
#135000000
1"
10
#140000000
0"
00
#145000000
1"
10
#150000000
0"
00
#155000000
1"
10
#160000000
0"
00
#165000000
1"
10
#170000000
0"
00
#175000000
1"
10
#180000000
0"
00
#185000000
1"
10
#190000000
0"
00
#195000000
1"
10
#200000000
0"
1#
00
12
#205000000
1"
1-
10
1<
b10011 ?
b10011 A
b1 B
#210000000
0"
00
#215000000
1"
10
b0 B
#220000000
0"
00
#225000000
1"
1,
10
1;
b10010 ?
#230000000
0"
00
#235000000
1"
10
b10001 ?
#240000000
0"
00
#245000000
1"
10
b10000 ?
#250000000
0"
00
#255000000
1"
0,
10
0;
b1111 ?
#260000000
0"
00
#265000000
1"
1,
10
1;
b1110 ?
#270000000
0"
00
#275000000
1"
10
b1101 ?
#280000000
0"
00
#285000000
1"
10
b1100 ?
#290000000
0"
00
#295000000
1"
0,
10
0;
b1011 ?
#300000000
0"
00
#305000000
1"
1,
10
1;
b1010 ?
#310000000
0"
00
#315000000
1"
10
b1001 ?
#320000000
0"
00
#325000000
1"
10
b1000 ?
#330000000
0"
00
#335000000
1"
0,
10
0;
b111 ?
#340000000
0"
00
#345000000
1"
1,
10
1;
b110 ?
#350000000
0"
00
#355000000
1"
10
b101 ?
#360000000
0"
00
#365000000
1"
10
b100 ?
#370000000
0"
00
#375000000
1"
0,
10
0;
b11 ?
#380000000
0"
00
#385000000
1"
1,
10
1;
b10 ?
#390000000
0"
00
#395000000
1"
10
b1 ?
#400000000
0"
00
#405000000
1"
10
b0 ?
#410000000
0"
00
#415000000
1"
0,
10
0;
b10100 ?
b110 @
#420000000
0"
00
#425000000
1"
10
b10011 ?
b1 B
#430000000
0"
00
#435000000
1"
10
b0 B
#440000000
0"
00
#445000000
1"
1,
10
1;
b10010 ?
#450000000
0"
00
#455000000
1"
10
b10001 ?
#460000000
0"
00
#465000000
1"
10
b10000 ?
#470000000
0"
00
#475000000
1"
0,
10
0;
b1111 ?
#480000000
0"
00
#485000000
1"
1,
10
1;
b1110 ?
#490000000
0"
00
#495000000
1"
10
b1101 ?
#500000000
0"
00
#505000000
1"
10
b1100 ?
#510000000
0"
00
#515000000
1"
0,
10
0;
b1011 ?
#520000000
0"
00
#525000000
1"
1,
10
1;
b1010 ?
#530000000
0"
00
#535000000
1"
10
b1001 ?
#540000000
0"
00
#545000000
1"
10
b1000 ?
#550000000
0"
00
#555000000
1"
0,
10
0;
b111 ?
#560000000
0"
00
#565000000
1"
1,
10
1;
b110 ?
#570000000
0"
00
#575000000
1"
10
b101 ?
#580000000
0"
00
#585000000
1"
10
b100 ?
#590000000
0"
00
#595000000
1"
0,
10
0;
b11 ?
#600000000
0"
00
#605000000
1"
1,
10
1;
b10 ?
#610000000
0"
00
#615000000
1"
10
b1 ?
#620000000
0"
00
#625000000
1"
10
b0 ?
#630000000
0"
00
#635000000
1"
0,
10
0;
b10100 ?
b101 @
#640000000
0"
00
#645000000
1"
10
b10011 ?
b1011 A
b1 B
#650000000
0"
00
#655000000
1"
10
b1011 ?
b0 B
#660000000
0"
00
#665000000
1"
1,
10
1;
b1010 ?
#670000000
0"
00
#675000000
1"
10
b1001 ?
#680000000
0"
00
#685000000
1"
10
b1000 ?
#690000000
0"
00
#695000000
1"
0,
10
0;
b111 ?
#700000000
0"
00
#705000000
1"
1,
10
1;
b110 ?
#710000000
0"
00
#715000000
1"
10
b101 ?
#720000000
0"
00
#725000000
1"
10
b100 ?
#730000000
0"
00
#735000000
1"
0,
10
0;
b11 ?
#740000000
0"
00
#745000000
1"
1,
10
1;
b10 ?
#750000000
0"
00
#755000000
1"
10
b1 ?
#760000000
0"
00
#765000000
1"
10
b0 ?
#770000000
0"
00
#775000000
1"
0,
10
0;
b10100 ?
b100 @
#780000000
0"
00
#785000000
1"
10
b10011 ?
b1001 A
b1 B
#790000000
0"
00
#795000000
1"
10
b1001 ?
b0 B
#800000000
0"
00
#805000000
1"
1,
10
1;
b1000 ?
#810000000
0"
00
#815000000
1"
0,
10
0;
b111 ?
#820000000
0"
00
#825000000
1"
1,
10
1;
b110 ?
#830000000
0"
00
#835000000
1"
10
b101 ?
#840000000
0"
00
#845000000
1"
10
b100 ?
#850000000
0"
00
#855000000
1"
0,
10
0;
b11 ?
#860000000
0"
00
#865000000
1"
1,
10
1;
b10 ?
#870000000
0"
00
#875000000
1"
0,
10
0;
b1 ?
#880000000
0"
00
#885000000
1"
1,
10
1;
b0 ?
#890000000
0"
00
#895000000
1"
0,
10
0;
b10100 ?
b11 @
#900000000
0"
00
#905000000
1"
10
b10011 ?
b101 A
b1 B
#910000000
0"
00
#915000000
1"
10
b101 ?
b0 B
#920000000
0"
00
#925000000
1"
1,
10
1;
b100 ?
#930000000
0"
00
#935000000
1"
0,
10
0;
b11 ?
#940000000
0"
00
#945000000
1"
1,
10
1;
b10 ?
#950000000
0"
00
#955000000
1"
10
b1 ?
#960000000
0"
00
#965000000
1"
10
b0 ?
#970000000
0"
00
#975000000
1"
0,
10
0;
b10100 ?
b10 @
#980000000
0"
00
#985000000
1"
10
b10011 ?
b111 A
b1 B
#990000000
0"
00
#995000000
1"
10
b111 ?
b0 B
#1000000000
0"
00
#1005000000
1"
1,
10
1;
b110 ?
#1010000000
0"
00
#1015000000
1"
0,
10
0;
b101 ?
#1020000000
0"
00
#1025000000
1"
1,
10
1;
b100 ?
#1030000000
0"
00
#1035000000
1"
0,
10
0;
b11 ?
#1040000000
0"
00
#1045000000
1"
1,
10
1;
b10 ?
#1050000000
0"
00
#1055000000
1"
10
b1 ?
#1060000000
0"
00
#1065000000
1"
10
b0 ?
#1070000000
0"
00
#1075000000
1"
0,
10
0;
b10100 ?
b1 @
#1080000000
0"
00
#1085000000
1"
10
b10011 ?
b1 B
#1090000000
0"
00
#1095000000
1"
10
b111 ?
b0 B
#1100000000
0"
00
#1105000000
1"
1,
10
1;
b110 ?
#1110000000
0"
00
#1115000000
1"
0,
10
0;
b101 ?
#1120000000
0"
00
#1125000000
1"
1,
10
1;
b100 ?
#1130000000
0"
00
#1135000000
1"
0,
10
0;
b11 ?
#1140000000
0"
00
#1145000000
1"
1,
10
1;
b10 ?
#1150000000
0"
00
#1155000000
1"
10
b1 ?
#1160000000
0"
00
#1165000000
1"
10
b0 ?
#1170000000
0"
00
#1175000000
1"
0,
10
0;
b10100 ?
b0 @
#1180000000
0"
00
#1185000000
1"
10
b10011 ?
b11 A
b1 B
#1190000000
0"
00
#1195000000
1"
10
b11 ?
b0 B
#1200000000
0"
00
#1205000000
1"
1,
10
1;
b10 ?
#1210000000
0"
00
#1215000000
1"
10
b1 ?
#1220000000
0"
00
#1225000000
1"
10
b0 ?
#1230000000
0"
00
#1235000000
1"
0,
10
0;
b10100 ?
b1000 @
#1240000000
0"
00
#1245000000
1"
0-
1.
10
0<
1=
b1 ?
#1250000000
0"
00
#1255000000
1"
10
#1260000000
0"
00
#1265000000
1"
10
#1270000000
0"
00
#1275000000
1"
10
#1280000000
0"
00
#1285000000
1"
10
#1290000000
0"
00
#1295000000
1"
10
#1300000000
0"
00
#1305000000
1"
10
#1310000000
0"
00
#1315000000
1"
10
#1320000000
0"
00
#1325000000
1"
10
#1330000000
0"
00
#1335000000
1"
10
#1340000000
0"
00
#1345000000
1"
10
#1350000000
0"
00
#1355000000
1"
10
#1360000000
0"
00
#1365000000
1"
10
#1370000000
0"
00
#1375000000
1"
10
#1380000000
0"
00
#1385000000
1"
10
#1390000000
0"
00
#1395000000
1"
10
#1400000000
0"
0#
0.
00
02
0=
b10100 ?
b111 @
b10100 A
#1405000000
1"
10
#1410000000
0"
00
#1415000000
1"
10
#1420000000
0"
00
#1425000000
1"
10
#1430000000
0"
00
#1435000000
1"
10
#1440000000
0"
00
#1445000000
1"
10
#1450000000
0"
00
#1455000000
1"
10
#1460000000
0"
00
#1465000000
1"
10
#1470000000
0"
00
#1475000000
1"
10
#1480000000
0"
00
#1485000000
1"
10
#1490000000
0"
00
#1495000000
1"
10
#1500000000
0"
00
#1505000000
1"
10
#1510000000
0"
00
#1515000000
1"
10
#1520000000
0"
00
#1525000000
1"
10
#1530000000
0"
00
#1535000000
1"
10
#1540000000
0"
00
#1545000000
1"
10
#1550000000
0"
00
#1555000000
1"
10
#1560000000
0"
00
#1565000000
1"
10
#1570000000
0"
00
#1575000000
1"
10
#1580000000
0"
00
#1585000000
1"
10
#1590000000
0"
00
#1595000000
1"
10
#1600000000
0"
1#
00
12
#1605000000
1"
1-
10
1<
b10011 ?
b10011 A
b1 B
#1610000000
0"
00
#1615000000
1"
10
b0 B
#1620000000
0"
00
#1625000000
1"
1,
10
1;
b10010 ?
#1630000000
0"
00
#1635000000
1"
10
b10001 ?
#1640000000
0"
00
#1645000000
1"
10
b10000 ?
#1650000000
0"
00
#1655000000
1"
0,
10
0;
b1111 ?
#1660000000
0"
00
#1665000000
1"
1,
10
1;
b1110 ?
#1670000000
0"
00
#1675000000
1"
10
b1101 ?
#1680000000
0"
00
#1685000000
1"
10
b1100 ?
#1690000000
0"
00
#1695000000
1"
0,
10
0;
b1011 ?
#1700000000
0"
00
#1705000000
1"
1,
10
1;
b1010 ?
#1710000000
0"
00
#1715000000
1"
10
b1001 ?
#1720000000
0"
00
#1725000000
1"
10
b1000 ?
#1730000000
0"
00
#1735000000
1"
0,
10
0;
b111 ?
#1740000000
0"
00
#1745000000
1"
1,
10
1;
b110 ?
#1750000000
0"
00
#1755000000
1"
10
b101 ?
#1760000000
0"
00
#1765000000
1"
10
b100 ?
#1770000000
0"
00
#1775000000
1"
0,
10
0;
b11 ?
#1780000000
0"
00
#1785000000
1"
1,
10
1;
b10 ?
#1790000000
0"
00
#1795000000
1"
10
b1 ?
#1800000000
0"
00
#1805000000
1"
10
b0 ?
#1810000000
0"
00
#1815000000
1"
0,
10
0;
b10100 ?
b110 @
#1820000000
0"
00
#1825000000
1"
10
b10011 ?
b1 B
#1830000000
0"
00
#1835000000
1"
10
b0 B
#1840000000
0"
00
#1845000000
1"
1,
10
1;
b10010 ?
#1850000000
0"
00
#1855000000
1"
10
b10001 ?
#1860000000
0"
00
#1865000000
1"
10
b10000 ?
#1870000000
0"
00
#1875000000
1"
0,
10
0;
b1111 ?
#1880000000
0"
00
#1885000000
1"
1,
10
1;
b1110 ?
#1890000000
0"
00
#1895000000
1"
10
b1101 ?
#1900000000
0"
00
#1905000000
1"
10
b1100 ?
#1910000000
0"
00
#1915000000
1"
0,
10
0;
b1011 ?
#1920000000
0"
00
#1925000000
1"
1,
10
1;
b1010 ?
#1930000000
0"
00
#1935000000
1"
10
b1001 ?
#1940000000
0"
00
#1945000000
1"
10
b1000 ?
#1950000000
0"
00
#1955000000
1"
0,
10
0;
b111 ?
#1960000000
0"
00
#1965000000
1"
1,
10
1;
b110 ?
#1970000000
0"
00
#1975000000
1"
10
b101 ?
#1980000000
0"
00
#1985000000
1"
10
b100 ?
#1990000000
0"
00
#1995000000
1"
0,
10
0;
b11 ?
#2000000000
0"
00
#2005000000
1"
1,
10
1;
b10 ?
#2010000000
0"
00
#2015000000
1"
10
b1 ?
#2020000000
0"
00
#2025000000
1"
10
b0 ?
#2030000000
0"
00
#2035000000
1"
0,
10
0;
b10100 ?
b101 @
#2040000000
0"
00
#2045000000
1"
10
b10011 ?
b1011 A
b1 B
#2050000000
0"
00
#2055000000
1"
10
b1011 ?
b0 B
#2060000000
0"
00
#2065000000
1"
1,
10
1;
b1010 ?
#2070000000
0"
00
#2075000000
1"
10
b1001 ?
#2080000000
0"
00
#2085000000
1"
10
b1000 ?
#2090000000
0"
00
#2095000000
1"
0,
10
0;
b111 ?
#2100000000
0"
00
#2105000000
1"
1,
10
1;
b110 ?
#2110000000
0"
00
#2115000000
1"
10
b101 ?
#2120000000
0"
00
#2125000000
1"
10
b100 ?
#2130000000
0"
00
#2135000000
1"
0,
10
0;
b11 ?
#2140000000
0"
00
#2145000000
1"
1,
10
1;
b10 ?
#2150000000
0"
00
#2155000000
1"
10
b1 ?
#2160000000
0"
00
#2165000000
1"
10
b0 ?
#2170000000
0"
00
#2175000000
1"
0,
10
0;
b10100 ?
b100 @
#2180000000
0"
00
#2185000000
1"
10
b10011 ?
b1001 A
b1 B
#2190000000
0"
00
#2195000000
1"
10
b1001 ?
b0 B
#2200000000
0"
00
#2205000000
1"
1,
10
1;
b1000 ?
#2210000000
0"
00
#2215000000
1"
0,
10
0;
b111 ?
#2220000000
0"
00
#2225000000
1"
1,
10
1;
b110 ?
#2230000000
0"
00
#2235000000
1"
10
b101 ?
#2240000000
0"
00
#2245000000
1"
10
b100 ?
#2250000000
0"
00
#2255000000
1"
0,
10
0;
b11 ?
#2260000000
0"
00
#2265000000
1"
1,
10
1;
b10 ?
#2270000000
0"
00
#2275000000
1"
0,
10
0;
b1 ?
#2280000000
0"
00
#2285000000
1"
1,
10
1;
b0 ?
#2290000000
0"
00
#2295000000
1"
0,
10
0;
b10100 ?
b11 @
#2300000000
0"
00
#2305000000
1"
10
b10011 ?
b101 A
b1 B
#2310000000
0"
00
#2315000000
1"
10
b101 ?
b0 B
#2320000000
0"
00
#2325000000
1"
1,
10
1;
b100 ?
#2330000000
0"
00
#2335000000
1"
0,
10
0;
b11 ?
#2340000000
0"
00
#2345000000
1"
1,
10
1;
b10 ?
#2350000000
0"
00
#2355000000
1"
10
b1 ?
#2360000000
0"
00
#2365000000
1"
10
b0 ?
#2370000000
0"
00
#2375000000
1"
0,
10
0;
b10100 ?
b10 @
#2380000000
0"
00
#2385000000
1"
10
b10011 ?
b111 A
b1 B
#2390000000
0"
00
#2395000000
1"
10
b111 ?
b0 B
#2400000000
0"
00
#2405000000
1"
1,
10
1;
b110 ?
#2410000000
0"
00
#2415000000
1"
0,
10
0;
b101 ?
#2420000000
0"
00
#2425000000
1"
1,
10
1;
b100 ?
#2430000000
0"
00
#2435000000
1"
0,
10
0;
b11 ?
#2440000000
0"
00
#2445000000
1"
1,
10
1;
b10 ?
#2450000000
0"
00
#2455000000
1"
10
b1 ?
#2460000000
0"
00
#2465000000
1"
10
b0 ?
#2470000000
0"
00
#2475000000
1"
0,
10
0;
b10100 ?
b1 @
#2480000000
0"
00
#2485000000
1"
10
b10011 ?
b1 B
#2490000000
0"
00
#2495000000
1"
10
b111 ?
b0 B
#2500000000
0"
00
#2505000000
1"
1,
10
1;
b110 ?
#2510000000
0"
00
#2515000000
1"
0,
10
0;
b101 ?
#2520000000
0"
00
#2525000000
1"
1,
10
1;
b100 ?
#2530000000
0"
00
#2535000000
1"
0,
10
0;
b11 ?
#2540000000
0"
00
#2545000000
1"
1,
10
1;
b10 ?
#2550000000
0"
00
#2555000000
1"
10
b1 ?
#2560000000
0"
00
#2565000000
1"
10
b0 ?
#2570000000
0"
00
#2575000000
1"
0,
10
0;
b10100 ?
b0 @
#2580000000
0"
00
#2585000000
1"
10
b10011 ?
b11 A
b1 B
#2590000000
0"
00
#2595000000
1"
10
b11 ?
b0 B
#2600000000
0"
00
#2605000000
1"
1,
10
1;
b10 ?
#2610000000
0"
00
#2615000000
1"
10
b1 ?
#2620000000
0"
00
#2625000000
1"
10
b0 ?
#2630000000
0"
00
#2635000000
1"
0,
10
0;
b10100 ?
b1000 @
#2640000000
0"
00
#2645000000
1"
0-
1.
10
0<
1=
b1 ?
#2650000000
0"
00
#2655000000
1"
10
#2660000000
0"
00
#2665000000
1"
10
#2670000000
0"
00
#2675000000
1"
10
#2680000000
0"
00
#2685000000
1"
10
#2690000000
0"
00
#2695000000
1"
10
#2700000000
0"
00
#2705000000
1"
10
#2710000000
0"
00
#2715000000
1"
10
#2720000000
0"
00
#2725000000
1"
10
#2730000000
0"
00
#2735000000
1"
10
#2740000000
0"
00
#2745000000
1"
10
#2750000000
0"
00
#2755000000
1"
10
#2760000000
0"
00
#2765000000
1"
10
#2770000000
0"
00
#2775000000
1"
10
#2780000000
0"
00
#2785000000
1"
10
#2790000000
0"
00
#2795000000
1"
10
#2800000000
0#
0.
02
0=
b10100 ?
b111 @
b10100 A
