extra/hex_7seg.vhd

library IEEE;
use IEEE.STD_LOGIC_1164.ALL;

entity hex_7seg is
    Port ( blank : in STD_LOGIC;
           hex : in STD_LOGIC_VECTOR (9 downto 0);
           seg : out STD_LOGIC_VECTOR (6 downto 0));
end hex_7seg;

architecture Behavioral of hex_7seg is

begin

  p_7seg_decoder : process (blank, hex) is

  begin
    if (blank = '1') then
      seg <= "1111111";     -- Blanking display
    else

      case hex is
        when "0000000111" =>
          seg <= "0001000"; -- A
          
        when "0011010101" =>
          seg <= "1100000"; -- B
          
        when "0011011101" =>
          seg <= "0110001"; -- C
          
        when "0000110101" =>
          seg <= "1000010"; -- D
          
        when "0000000001" =>
          seg <= "0110000"; -- E
         
         when "0001011101" =>
          seg <= "0111000"; -- F
          
         when "0000111101" =>
          seg <= "0100001"; -- G
          
         when "0001010101" =>
          seg <= "1101000"; -- H
         
         when "0000000101" =>
          seg <= "1001111"; -- I
         
         when "0001111111" =>
          seg <= "1000011"; -- J
          
         when "0000110111" =>
          seg <= "0101000"; -- K
          
         when "0001110101" =>
          seg <= "1110001"; -- L
          
         when "0000001111" =>
          seg <= "0101011"; -- M
          
         when "0000001101" =>
          seg <= "1101010"; -- N
          
         when "0000111111" =>
          seg <= "1100010"; -- O
         
         when "0001111101" =>
          seg <= "0011000"; -- P
          
         when "0011110111" =>
          seg <= "0001100"; -- Q
          
         when "0000011101" =>
          seg <= "1111010"; -- R
          
         when "0000010101" =>
          seg <= "0100101"; -- S
          
         when "0000000011" =>
          seg <= "1110000"; -- T
         
         when "0000010111" =>
          seg <= "1000001"; -- U
          
         when "0001010111" =>
          seg <= "1100011"; -- V
          
         when "0000011111" =>
          seg <= "1010101"; -- W
          
         when "0011010111" =>
          seg <= "1001000"; -- X
          
         when "0011011111" =>
          seg <= "1000100"; -- Y
          
         when "0011110101" =>
          seg <= "0010011"; -- Z
          
         when "0111111111" =>
          seg <= "1111001"; -- 1
          
         when "0101111111" =>
          seg <= "0010010"; -- 2
         
         when "0101011111" =>
          seg <= "0000110"; -- 3
          
         when "0101010111" =>
          seg <= "1001100"; -- 4
         
         when "0101010101" =>
          seg <= "0100100"; -- 5
          
         when "1101010101" =>
          seg <= "0100000"; -- 6
          
         when "1111010101" =>
          seg <= "0001111"; -- 7
          
         when "1111110101" =>
          seg <= "0000000"; -- 8
          
         when "1111111101" =>
          seg <= "0000100"; -- 9
          
         when "1111111111" =>
          seg <= "0000001"; -- 0
          
         when "0000000000" =>
          seg <= "1111111";  
          
         when others =>

          seg <= "1111110"; -- -

      end case;

    end if;

  end process p_7seg_decoder;

end Behavioral;

proj/cnt_up_down.vhd

library ieee;
  use ieee.std_logic_1164.all;
  use ieee.numeric_std.all;

----------------------------------------------------------
-- Entity declaration for N-bit counter
----------------------------------------------------------

entity cnt_up_down is
  generic (
    g_CNT_WIDTH : natural := 3 --! Default number of counter bits
  );
  port (
    clk    : in    std_logic; --! Main clock
    rst    : in    std_logic; --! Synchronous reset
    en     : in    std_logic; --! Enable input
    cnt_up : in    std_logic; --! Direction of the counter
    cnt    : out   std_logic_vector(g_CNT_WIDTH - 1 downto 0)
  );
end entity cnt_up_down;

----------------------------------------------------------
-- Architecture body for N-bit counter
----------------------------------------------------------

architecture behavioral of cnt_up_down is

  signal sig_cnt : unsigned(g_CNT_WIDTH - 1 downto 0); --! Local counter

begin

  --------------------------------------------------------
  -- p_cnt_up_down:
  -- Clocked process with synchronous reset which implements
  -- n-bit up/down counter.
  --------------------------------------------------------
  p_cnt_up_down : process (clk) is
  begin

    if rising_edge(clk) then
      if (rst = '1') then           -- Synchronous reset
        sig_cnt <= (others => '0'); -- Clear all bits
      elsif (en = '1') then         -- Test if counter is enabled

        -- TEST COUNTER DIRECTION HERE
        if (cnt_up = '1') then 
           sig_cnt <= sig_cnt + 1;
        else 
           sig_cnt <= sig_cnt - 1;
        end if;
      end if;
  end if;

 end process p_cnt_up_down;

  -- Output must be retyped from "unsigned" to "std_logic_vector"
  cnt <= std_logic_vector(sig_cnt);

end architecture behavioral;

src/clock_enable.vhd

----------------------------------------------------------
library ieee;
  use ieee.std_logic_1164.all;
  use ieee.numeric_std.all; -- Package for arithmetic operations

----------------------------------------------------------
-- Entity declaration for clock enable
----------------------------------------------------------

entity clock_enable is
  generic (
    g_MAX : natural := 200000 --! Number of clk pulses to generate one enable signal period
  );                       -- Note that there IS a semicolon between generic and port sections
  port (
    clk : in    std_logic; --! Main clock
    rst : in    std_logic; --! High-active synchronous reset
    ce  : out   std_logic  --! Clock enable pulse signal
  );
end entity clock_enable;

------------------------------------------------------------
-- Architecture body for clock enable
------------------------------------------------------------

architecture behavioral of clock_enable is

  -- Local counter
  signal sig_cnt : natural;

begin

  --------------------------------------------------------
  -- p_clk_enable:
  -- Generate clock enable signal. By default, enable signal
  -- is low and generated pulse is always one clock long.
  --------------------------------------------------------
  p_clk_enable : process (clk) is
  begin

    if rising_edge(clk) then              -- Synchronous process
      if (rst = '1') then                 -- High-active reset
        sig_cnt <= 0;                     -- Clear local counter
        ce      <= '0';                   -- Set output to low

      -- Test number of clock periods
      elsif (sig_cnt >= (g_MAX - 1)) then
        sig_cnt <= 0;                     -- Clear local counter
        ce      <= '1';                   -- Generate clock enable pulse
      else
        sig_cnt <= sig_cnt + 1;
        ce      <= '0';
      end if;
    end if;

  end process p_clk_enable;

end architecture behavioral;

extra/driver_display.vhd

library ieee;
  use ieee.std_logic_1164.all;
  use ieee.numeric_std.all;

----------------------------------------------------------

entity driver_display is
  port (
    clk     : in    std_logic;
    rst     : in    std_logic;
    data1   : in    std_logic_vector(9 downto 0);
    data2   : in    std_logic_vector(9 downto 0);
    data3   : in    std_logic_vector(9 downto 0);
    data4   : in    std_logic_vector(9 downto 0);
    data5   : in    std_logic_vector(9 downto 0);
    data6   : in    std_logic_vector(9 downto 0);
    data7   : in    std_logic_vector(9 downto 0);
    data8   : in    std_logic_vector(9 downto 0);
    seg     : out   std_logic_vector(6 downto 0);
    dig     : out   std_logic_vector(7 downto 0)
  );
end entity driver_display;


architecture behavioral of driver_display is

  -- Internal clock enable
  signal sig_en_2ms : std_logic;

  -- Internal 3-bit counter for multiplexing 8 digits
  signal sig_cnt_3bit : std_logic_vector(2 downto 0);

  -- Internal 8-bit value for 7-segment decoder
  signal sig_hex : std_logic_vector(9 downto 0);

begin

  clk_en0 : entity work.clock_enable
    generic map (
      g_MAX => 200000
    )
    port map (
      clk => clk,
      rst => rst,
      ce  => sig_en_2ms
    );

  bin_cnt0 : entity work.cnt_up_down
    generic map (
      g_CNT_WIDTH => 3
    )
    port map (
      clk => clk,
      rst => rst,
      en => sig_en_2ms,
      cnt_up => '0',
      cnt => sig_cnt_3bit
      
    );


  hex2seg : entity work.hex_7seg
    port map (
      blank => rst,
      hex   => sig_hex,
      seg   => seg
    );

  --------------------------------------------------------
  -- p_mux:
  -- A sequential process that implements a multiplexer for
  -- selecting data for a single digit, a decimal point,
  -- and switches the common anodes of each display.
  --------------------------------------------------------
  p_mux : process (clk) is
  begin

    if (rising_edge(clk)) then
      if (rst = '1') then
        sig_hex <= data1;
        dig     <= "11111110";
      else

        case sig_cnt_3bit is

          when "111" =>
            sig_hex <= data8;
            dig     <= "01111111";

          when "110" =>
            sig_hex <= data7;
            dig     <= "10111111";

          when "101" =>
            sig_hex <= data6;
            dig     <= "11011111";
            
          when "100" =>
            sig_hex <= data5;
            dig     <= "11101111";
            
          when "011" =>
            sig_hex <= data4;
            dig     <= "11110111";
          
          when "010" =>
            sig_hex <= data3;
            dig     <= "11111011";
            
          when "001" =>
            sig_hex <= data2;
            dig     <= "11111101";
            
          when others =>
            sig_hex <= data1;
            dig     <= "11111110";

        end case;

      end if;
    end if;

  end process p_mux;

end architecture behavioral;

extra/tb_driver_display.vhd
library ieee;
  use ieee.std_logic_1164.all;


entity tb_driver_display is
  -- Entity of testbench is always empty
end entity tb_driver_display;


architecture testbench of tb_driver_display is

  -- Testbench local constants
  constant c_CLK_100MHZ_PERIOD : time := 10 ns;

  -- Testench local signals
  signal sig_clk_100mhz : std_logic;
  signal sig_rst        : std_logic;
  signal sig_data1      : std_logic_vector(9 downto 0);
  signal sig_data2      : std_logic_vector(9 downto 0);
  signal sig_data3      : std_logic_vector(9 downto 0);
  signal sig_data4      : std_logic_vector(9 downto 0);
  signal sig_data5      : std_logic_vector(9 downto 0);
  signal sig_data6      : std_logic_vector(9 downto 0);
  signal sig_data7      : std_logic_vector(9 downto 0);
  signal sig_data8      : std_logic_vector(9 downto 0);
  signal sig_seg        : std_logic_vector(6 downto 0);
  signal sig_dig        : std_logic_vector(7 downto 0);

begin

 
  uut_driver_display : entity work.driver_display
    port map (
      clk     => sig_clk_100mhz,
      rst     => sig_rst,
      data1   => sig_data1,
      data2   => sig_data2,
      data3   => sig_data3,
      data4   => sig_data4,
      data5   => sig_data5,
      data6   => sig_data6,
      data7   => sig_data7,
      data8   => sig_data8,
      seg     => sig_seg,
      dig     => sig_dig
    );

  --------------------------------------------------------
  -- Clock generation process
  --------------------------------------------------------
  p_clk_gen : process is
  begin

    while now < 400 ns loop -- 40 periods of 100MHz clock

      sig_clk_100mhz <= '0';
      wait for c_CLK_100MHZ_PERIOD / 2;
      sig_clk_100mhz <= '1';
      wait for c_CLK_100MHZ_PERIOD / 2;

    end loop;
    wait;

  end process p_clk_gen;

  --------------------------------------------------------
  -- Reset generation process
  --------------------------------------------------------
  p_reset_gen : process is
  begin

    sig_rst <= '0';
    wait for 15 ns;
    sig_rst <= '1';
    wait for 70 ns;
    sig_rst <= '0';
    wait;

  end process p_reset_gen;

  --------------------------------------------------------
  -- Data generation process
  --------------------------------------------------------
  p_stimulus : process is
  begin

    report "Stimulus process started";
    sig_data8 <= "0001010111"; -- V
    sig_data7 <= "0001110101"; -- L
    sig_data6 <= "0000000111"; -- A
    sig_data5 <= "0000110101"; -- D
    sig_data4 <= "0000000101"; -- I
    sig_data3 <= "0000110111"; -- K
    sig_data2 <= "1111111111"; -- 0
    sig_data1 <= "0111111111"; -- 1

    report "Stimulus process finished";
    wait;

  end process p_stimulus;

end architecture testbench;

extra/waveforms/driver_display.vcd
$date
  Mon Apr 17 08:04:52 2023
$end
$version
  GHDL v0
$end
$timescale
  1 fs
$end
$scope module standard $end
$upscope $end
$scope module std_logic_1164 $end
$upscope $end
$scope module numeric_std $end
$upscope $end
$scope module tb_driver_display $end
$var reg 1 ! sig_clk_100mhz $end
$var reg 1 " sig_rst $end
$var reg 10 # sig_data1[9:0] $end
$var reg 10 $ sig_data2[9:0] $end
$var reg 10 % sig_data3[9:0] $end
$var reg 10 & sig_data4[9:0] $end
$var reg 10 ' sig_data5[9:0] $end
$var reg 10 ( sig_data6[9:0] $end
$var reg 10 ) sig_data7[9:0] $end
$var reg 10 * sig_data8[9:0] $end
$var reg 7 + sig_seg[6:0] $end
$var reg 8 , sig_dig[7:0] $end
$scope module uut_driver_display $end
$var reg 1 - clk $end
$var reg 1 . rst $end
$var reg 10 / data1[9:0] $end
$var reg 10 0 data2[9:0] $end
$var reg 10 1 data3[9:0] $end
$var reg 10 2 data4[9:0] $end
$var reg 10 3 data5[9:0] $end
$var reg 10 4 data6[9:0] $end
$var reg 10 5 data7[9:0] $end
$var reg 10 6 data8[9:0] $end
$var reg 7 7 seg[6:0] $end
$var reg 8 8 dig[7:0] $end
$var reg 1 9 sig_en_2ms $end
$var reg 3 : sig_cnt_3bit[2:0] $end
$var reg 10 ; sig_hex[9:0] $end
$scope module clk_en0 $end
$var reg 1 < clk $end
$var reg 1 = rst $end
$var reg 1 > ce $end
$var integer 32 ? sig_cnt $end
$upscope $end
$scope module bin_cnt0 $end
$var reg 1 @ clk $end
$var reg 1 A rst $end
$var reg 1 B en $end
$var reg 1 C cnt_up $end
$var reg 3 D cnt[2:0] $end
$var reg 3 E sig_cnt[2:0] $end
$upscope $end
$scope module hex2seg $end
$var reg 1 F blank $end
$var reg 10 G hex[9:0] $end
$var reg 7 H seg[6:0] $end
$upscope $end
$upscope $end
$upscope $end
$enddefinitions $end
#0
0!
0"
b0111111111 #
b1111111111 $
b0000110111 %
b0000000101 &
b0000110101 '
b0000000111 (
b0001110101 )
b0001010111 *
b1111110 +
bUUUUUUUU ,
0-
0.
b0111111111 /
b1111111111 0
b0000110111 1
b0000000101 2
b0000110101 3
b0000000111 4
b0001110101 5
b0001010111 6
b1111110 7
bUUUUUUUU 8
U9
bUUU :
bUUUUUUUUUU ;
0<
0=
U>
b0 ?
0@
0A
UB
0C
bUUU D
bUUU E
0F
bUUUUUUUUUU G
b1111110 H
#5000000
1!
b1111001 +
b11111110 ,
1-
b1111001 7
b11111110 8
19
b0111111111 ;
1<
1>
1@
1B
b0111111111 G
b1111001 H
#10000000
0!
0-
0<
0@
#15000000
1!
1"
b1111111 +
1-
1.
b1111111 7
09
b000 :
1<
1=
0>
1@
1A
0B
b000 D
b000 E
1F
b1111111 H
#20000000
0!
0-
0<
0@
#25000000
1!
1-
1<
1@
#30000000
0!
0-
0<
0@
#35000000
1!
1-
1<
1@
#40000000
0!
0-
0<
0@
#45000000
1!
1-
1<
1@
#50000000
0!
0-
0<
0@
#55000000
1!
1-
1<
1@
#60000000
0!
0-
0<
0@
#65000000
1!
1-
1<
1@
#70000000
0!
0-
0<
0@
#75000000
1!
1-
1<
1@
#80000000
0!
0-
0<
0@
#85000000
1!
0"
b1111001 +
1-
0.
b1111001 7
19
1<
0=
1>
1@
0A
1B
0F
b1111001 H
#90000000
0!
0-
0<
0@
#95000000
1!
1-
b111 :
1<
1@
b111 D
b111 E
#100000000
0!
0-
0<
0@
#105000000
1!
b1100011 +
b01111111 ,
1-
b1100011 7
b01111111 8
b110 :
b0001010111 ;
1<
1@
b110 D
b110 E
b0001010111 G
b1100011 H
#110000000
0!
0-
0<
0@
#115000000
1!
b1110001 +
b10111111 ,
1-
b1110001 7
b10111111 8
b101 :
b0001110101 ;
1<
1@
b101 D
b101 E
b0001110101 G
b1110001 H
#120000000
0!
0-
0<
0@
#125000000
1!
b0001000 +
b11011111 ,
1-
b0001000 7
b11011111 8
b100 :
b0000000111 ;
1<
1@
b100 D
b100 E
b0000000111 G
b0001000 H
#130000000
0!
0-
0<
0@
#135000000
1!
b1000010 +
b11101111 ,
1-
b1000010 7
b11101111 8
b011 :
b0000110101 ;
1<
1@
b011 D
b011 E
b0000110101 G
b1000010 H
#140000000
0!
0-
0<
0@
#145000000
1!
b1001111 +
b11110111 ,
1-
b1001111 7
b11110111 8
b010 :
b0000000101 ;
1<
1@
b010 D
b010 E
b0000000101 G
b1001111 H
#150000000
0!
0-
0<
0@
#155000000
1!
b0101000 +
b11111011 ,
1-
b0101000 7
b11111011 8
b001 :
b0000110111 ;
1<
1@
b001 D
b001 E
b0000110111 G
b0101000 H
#160000000
0!
0-
0<
0@
#165000000
1!
b0000001 +
b11111101 ,
1-
b0000001 7
b11111101 8
b000 :
b1111111111 ;
1<
1@
b000 D
b000 E
b1111111111 G
b0000001 H
#170000000
0!
0-
0<
0@
#175000000
1!
b1111001 +
b11111110 ,
1-
b1111001 7
b11111110 8
b111 :
b0111111111 ;
1<
1@
b111 D
b111 E
b0111111111 G
b1111001 H
#180000000
0!
0-
0<
0@
#185000000
1!
b1100011 +
b01111111 ,
1-
b1100011 7
b01111111 8
b110 :
b0001010111 ;
1<
1@
b110 D
b110 E
b0001010111 G
b1100011 H
#190000000
0!
0-
0<
0@
#195000000
1!
b1110001 +
b10111111 ,
1-
b1110001 7
b10111111 8
b101 :
b0001110101 ;
1<
1@
b101 D
b101 E
b0001110101 G
b1110001 H
#200000000
0!
0-
0<
0@
#205000000
1!
b0001000 +
b11011111 ,
1-
b0001000 7
b11011111 8
b100 :
b0000000111 ;
1<
1@
b100 D
b100 E
b0000000111 G
b0001000 H
#210000000
0!
0-
0<
0@
#215000000
1!
b1000010 +
b11101111 ,
1-
b1000010 7
b11101111 8
b011 :
b0000110101 ;
1<
1@
b011 D
b011 E
b0000110101 G
b1000010 H
#220000000
0!
0-
0<
0@
#225000000
1!
b1001111 +
b11110111 ,
1-
b1001111 7
b11110111 8
b010 :
b0000000101 ;
1<
1@
b010 D
b010 E
b0000000101 G
b1001111 H
#230000000
0!
0-
0<
0@
#235000000
1!
b0101000 +
b11111011 ,
1-
b0101000 7
b11111011 8
b001 :
b0000110111 ;
1<
1@
b001 D
b001 E
b0000110111 G
b0101000 H
#240000000
0!
0-
0<
0@
#245000000
1!
b0000001 +
b11111101 ,
1-
b0000001 7
b11111101 8
b000 :
b1111111111 ;
1<
1@
b000 D
b000 E
b1111111111 G
b0000001 H
#250000000
0!
0-
0<
0@
#255000000
1!
b1111001 +
b11111110 ,
1-
b1111001 7
b11111110 8
b111 :
b0111111111 ;
1<
1@
b111 D
b111 E
b0111111111 G
b1111001 H
#260000000
0!
0-
0<
0@
#265000000
1!
b1100011 +
b01111111 ,
1-
b1100011 7
b01111111 8
b110 :
b0001010111 ;
1<
1@
b110 D
b110 E
b0001010111 G
b1100011 H
#270000000
0!
0-
0<
0@
#275000000
1!
b1110001 +
b10111111 ,
1-
b1110001 7
b10111111 8
b101 :
b0001110101 ;
1<
1@
b101 D
b101 E
b0001110101 G
b1110001 H
#280000000
0!
0-
0<
0@
#285000000
1!
b0001000 +
b11011111 ,
1-
b0001000 7
b11011111 8
b100 :
b0000000111 ;
1<
1@
b100 D
b100 E
b0000000111 G
b0001000 H
#290000000
0!
0-
0<
0@
#295000000
1!
b1000010 +
b11101111 ,
1-
b1000010 7
b11101111 8
b011 :
b0000110101 ;
1<
1@
b011 D
b011 E
b0000110101 G
b1000010 H
#300000000
0!
0-
0<
0@
#305000000
1!
b1001111 +
b11110111 ,
1-
b1001111 7
b11110111 8
b010 :
b0000000101 ;
1<
1@
b010 D
b010 E
b0000000101 G
b1001111 H
#310000000
0!
0-
0<
0@
#315000000
1!
b0101000 +
b11111011 ,
1-
b0101000 7
b11111011 8
b001 :
b0000110111 ;
1<
1@
b001 D
b001 E
b0000110111 G
b0101000 H
#320000000
0!
0-
0<
0@
#325000000
1!
b0000001 +
b11111101 ,
1-
b0000001 7
b11111101 8
b000 :
b1111111111 ;
1<
1@
b000 D
b000 E
b1111111111 G
b0000001 H
#330000000
0!
0-
0<
0@
#335000000
1!
b1111001 +
b11111110 ,
1-
b1111001 7
b11111110 8
b111 :
b0111111111 ;
1<
1@
b111 D
b111 E
b0111111111 G
b1111001 H
#340000000
0!
0-
0<
0@
#345000000
1!
b1100011 +
b01111111 ,
1-
b1100011 7
b01111111 8
b110 :
b0001010111 ;
1<
1@
b110 D
b110 E
b0001010111 G
b1100011 H
#350000000
0!
0-
0<
0@
#355000000
1!
b1110001 +
b10111111 ,
1-
b1110001 7
b10111111 8
b101 :
b0001110101 ;
1<
1@
b101 D
b101 E
b0001110101 G
b1110001 H
#360000000
0!
0-
0<
0@
#365000000
1!
b0001000 +
b11011111 ,
1-
b0001000 7
b11011111 8
b100 :
b0000000111 ;
1<
1@
b100 D
b100 E
b0000000111 G
b0001000 H
#370000000
0!
0-
0<
0@
#375000000
1!
b1000010 +
b11101111 ,
1-
b1000010 7
b11101111 8
b011 :
b0000110101 ;
1<
1@
b011 D
b011 E
b0000110101 G
b1000010 H
#380000000
0!
0-
0<
0@
#385000000
1!
b1001111 +
b11110111 ,
1-
b1001111 7
b11110111 8
b010 :
b0000000101 ;
1<
1@
b010 D
b010 E
b0000000101 G
b1001111 H
#390000000
0!
0-
0<
0@
#395000000
1!
b0101000 +
b11111011 ,
1-
b0101000 7
b11111011 8
b001 :
b0000110111 ;
1<
1@
b001 D
b001 E
b0000110111 G
b0101000 H
