extra/morse_sender.vhd
library ieee;
  use ieee.std_logic_1164.all;
  use ieee.numeric_std.all;


entity morse_sender is
    port(
    clk        : in  std_logic;
    rst        : in  std_logic;
    send       : in  std_logic;
    data1      : in  std_logic_vector(9 downto 0);
    data2      : in  std_logic_vector(9 downto 0);
    data3      : in  std_logic_vector(9 downto 0);
    data4      : in  std_logic_vector(9 downto 0);
    data5      : in  std_logic_vector(9 downto 0);
    data6      : in  std_logic_vector(9 downto 0);
    data7      : in  std_logic_vector(9 downto 0);
    data8      : in  std_logic_vector(9 downto 0);
    output     : out  std_logic;
    led    : out  std_logic
    );
end entity morse_sender;

architecture Behavioral of morse_sender is
    signal data_cnt : integer range 0 to 8 := 0;
    signal zero_cnt : integer := 0;
    signal data_ind : integer range 0 to 20 := 20;
    signal data_1 : std_logic_vector(20 downto 0) := "000000000000000000000";
    signal data : std_logic_vector(9 downto 0) := "0000000000";
    begin
        p_morse_sender : process (clk,send) is
            begin
                case data_cnt is
                    when 0 =>
                    data <= data1;
                    when 1 =>
                    data <= data2;
                    when 2 =>
                    data <= data3;
                    when 3 =>
                    data <= data4;
                    when 4 =>
                    data <= data5;
                    when 5 =>
                    data <= data6;
                    when 6 =>
                    data <= data7;
                    when 7 =>
                    data <= data8;
                    when others =>
                    data <= "0000000000";
                    led <= '1';
                end case;
                case data(1 downto 0) is
                    when "01" => 
                    data_1(3 downto 0) <= "0010";
                    when "11" => 
                    data_1(3 downto 0) <= "1110";
                    when others => 
                    data_1(3 downto 0) <= "0000";
                end case;
                case data(3 downto 2) is
                    when "01" => 
                    data_1(7 downto 4) <= "0010";
                    when "11" => 
                    data_1(7 downto 4) <= "1110";
                    when others => 
                    data_1(7 downto 4) <= "0000";
                end case;
                case data(5 downto 4) is
                    when "01" => 
                    data_1(11 downto 8) <= "0010";
                    when "11" => 
                    data_1(11 downto 8) <= "1110";
                    when others => 
                    data_1(11 downto 8) <= "0000";
                end case;
                case data(7 downto 6) is
                    when "01" => 
                    data_1(15 downto 12) <= "0010";
                    when "11" => 
                    data_1(15 downto 12) <= "1110";
                    when others => 
                    data_1(15 downto 12) <= "0000";
                end case;
                case data(9 downto 8) is
                    when "01" => 
                    data_1(19 downto 16) <= "0010";
                    when "11" => 
                    data_1(19 downto 16) <= "1110";
                    when others => 
                    data_1(19 downto 16) <= "0000";
                end case;
                if (rst = '1') then
                    output <= '0';
                    led <= '0';
                    data <= "0000000000";
                    data_1 <= "000000000000000000000";
                    data_cnt <= 0;
                elsif (send = '1') then
                    if rising_edge(clk) and (data_cnt /= 8) then
                        if (data_1(data_ind)) = '1' then
                            zero_cnt <= 0;
                            output <= '1';
                            data_ind <= (data_ind - 1) mod 21;
                        else
                            zero_cnt <= zero_cnt + 1;
                            if (zero_cnt = 2) then
                                if (data_1((data_ind - 1) mod 21)) = '1' then
                                    data_ind <= (data_ind - 1) mod 21;
                                elsif (data_1((data_ind - 2) mod 21)) = '1' then
                                    data_ind <= (data_ind - 2) mod 21;
                                elsif (data_1((data_ind - 3) mod 21)) = '1' then
                                    data_ind <= (data_ind - 3) mod 21;
                                elsif (data_1((data_ind - 4) mod 21)) = '1' then
                                    data_ind <= (data_ind - 4) mod 21;
                                elsif (data_1((data_ind - 5) mod 21)) = '1' then
                                    data_ind <= (data_ind - 5) mod 21;
                                elsif (data_1((data_ind - 6) mod 21)) = '1' then
                                    data_ind <= (data_ind - 6) mod 21;
                                elsif (data_1((data_ind - 7) mod 21)) = '1' then
                                    data_ind <= (data_ind - 7) mod 21;
                                elsif (data_1((data_ind - 8) mod 21)) = '1' then
                                    data_ind <= (data_ind - 8) mod 21;
                                elsif (data_1((data_ind - 9) mod 21)) = '1' then
                                    data_ind <= (data_ind - 9) mod 21;
                                elsif (data_1((data_ind - 10) mod 21)) = '1' then
                                    data_ind <= (data_ind - 10) mod 21;
                                elsif (data_1((data_ind - 11) mod 21)) = '1' then
                                    data_ind <= (data_ind - 11) mod 21;
                                elsif (data_1((data_ind - 12) mod 21)) = '1' then
                                    data_ind <= (data_ind - 12) mod 21;
                                else
                                end if;
                                zero_cnt <= 0;
                                output <= '0';
                            else
                                output <= '0';
                                data_ind <= (data_ind - 1) mod 21;
                            end if;
                        end if;
                        if (data_ind = 0) then
                            data_ind <= (data_ind - 1) mod 21;
                            data_cnt <= (data_cnt + 1) mod 9;
                        end if;
                    end if;
                elsif (send = '0') then
                    output <= '0';
                    led <= '0';
                    data <= "0000000000";
                    data_1 <= "000000000000000000000";
                    data_cnt <= 0;
                end if;
            end process p_morse_sender;
    end architecture Behavioral;

extra/tb_morse_sender.vhd
library ieee;
  use ieee.std_logic_1164.all;
  use ieee.numeric_std.all;


entity tb_morse_sender is
--  Port ( );
end tb_morse_sender;

architecture testbench of tb_morse_sender is

    constant c_CLK_100MHZ_PERIOD : time := 10 ns;

    signal rst               : std_logic;
    signal sig_clk_100mhz    : std_logic;
    signal send       : std_logic;
    signal data1      : std_logic_vector(9 downto 0);
    signal data2      : std_logic_vector(9 downto 0);
    signal data3      : std_logic_vector(9 downto 0);
    signal data4      : std_logic_vector(9 downto 0);
    signal data5      : std_logic_vector(9 downto 0);
    signal data6      : std_logic_vector(9 downto 0);
    signal data7      : std_logic_vector(9 downto 0);
    signal data8      : std_logic_vector(9 downto 0);
    signal output     : std_logic;
    signal led        : std_logic;


begin
    uut_morse_sender: entity work.morse_sender
        port map(
            rst        => rst,
            clk        => sig_clk_100mhz,
            send       => send,
            data1      => data1,
            data2      => data2,
            data3      => data3,
            data4      => data4,
            data5      => data5,
            data6      => data6,
            data7      => data7,
            data8      => data8,
            output     => output,
            led        => led
        );
        
    p_clk_gen : process is
    begin
          
        while now < 3800 ns loop -- 200 periods of 100MHz clock
          
             sig_clk_100mhz <= '0';
             wait for c_CLK_100MHZ_PERIOD / 2;
             sig_clk_100mhz <= '1';
             wait for c_CLK_100MHZ_PERIOD / 2;
          
        end loop;
        wait;
          
    end process p_clk_gen;

    p_reset_gen : process is
    begin
      
        rst <= '0';
        wait for 10 ns;
        rst <= '1';
        wait for 90 ns;
        rst <= '0';
        wait for 10 ns;
        wait;
      
    end process p_reset_gen;


    p_stimulus : process
    begin 
        data8 <= "0001010111"; 
        data7 <= "0001110101"; 
        data6 <= "0000000111"; 
        data5 <= "0000110101"; 
        data4 <= "1111111111"; 
        data3 <= "1111111111"; 
        data2 <= "0011111111"; 
        data1 <= "0000111111"; 
        send <= '0';
        wait for 200 ns;
        send <= '1';
        wait for 1800 ns;
        send <= '0';
        wait for 200 ns;
        send <= '1';
        wait for 1200 ns;
        send <= '0';
        wait;
    end process p_stimulus;
end architecture testbench;

extra/waveforms/morse_sender.vcd
$date
  Mon Apr 17 18:47:30 2023
$end
$version
  GHDL v0
$end
$timescale
  1 fs
$end
$scope module standard $end
$upscope $end
$scope module std_logic_1164 $end
$upscope $end
$scope module numeric_std $end
$upscope $end
$scope module tb_morse_sender $end
$var reg 1 ! rst $end
$var reg 1 " sig_clk_100mhz $end
$var reg 1 # send $end
$var reg 10 $ data1[9:0] $end
$var reg 10 % data2[9:0] $end
$var reg 10 & data3[9:0] $end
$var reg 10 ' data4[9:0] $end
$var reg 10 ( data5[9:0] $end
$var reg 10 ) data6[9:0] $end
$var reg 10 * data7[9:0] $end
$var reg 10 + data8[9:0] $end
$var reg 1 , output $end
$var reg 1 - led $end
$scope module uut_morse_sender $end
$var reg 1 . clk $end
$var reg 1 / rst $end
$var reg 1 0 send $end
$var reg 10 1 data1[9:0] $end
$var reg 10 2 data2[9:0] $end
$var reg 10 3 data3[9:0] $end
$var reg 10 4 data4[9:0] $end
$var reg 10 5 data5[9:0] $end
$var reg 10 6 data6[9:0] $end
$var reg 10 7 data7[9:0] $end
$var reg 10 8 data8[9:0] $end
$var reg 1 9 output $end
$var reg 1 : led $end
$var integer 32 ; data_cnt $end
$var integer 32 < zero_cnt $end
$var integer 32 = data_ind $end
$var reg 21 > data_1[20:0] $end
$var reg 10 ? data[9:0] $end
$upscope $end
$upscope $end
$enddefinitions $end
#0
0!
0"
0#
b0000111111 $
b0011111111 %
b1111111111 &
b1111111111 '
b0000110101 (
b0000000111 )
b0001110101 *
b0001010111 +
0,
0-
0.
0/
00
b0000111111 1
b0011111111 2
b1111111111 3
b1111111111 4
b0000110101 5
b0000000111 6
b0001110101 7
b0001010111 8
09
0:
b0 ;
b0 <
b10100 =
b000000000000000000000 >
b0000000000 ?
#5000000
1"
1.
#10000000
1!
0"
0.
1/
#15000000
1"
1.
#20000000
0"
0.
#25000000
1"
1.
#30000000
0"
0.
#35000000
1"
1.
#40000000
0"
0.
#45000000
1"
1.
#50000000
0"
0.
#55000000
1"
1.
#60000000
0"
0.
#65000000
1"
1.
#70000000
0"
0.
#75000000
1"
1.
#80000000
0"
0.
#85000000
1"
1.
#90000000
0"
0.
#95000000
1"
1.
#100000000
0!
0"
0.
0/
#105000000
1"
1.
#110000000
0"
0.
#115000000
1"
1.
#120000000
0"
0.
#125000000
1"
1.
#130000000
0"
0.
#135000000
1"
1.
#140000000
0"
0.
#145000000
1"
1.
#150000000
0"
0.
#155000000
1"
1.
#160000000
0"
0.
#165000000
1"
1.
#170000000
0"
0.
#175000000
1"
1.
#180000000
0"
0.
#185000000
1"
1.
#190000000
0"
0.
#195000000
1"
1.
#200000000
0"
1#
0.
10
b0000111111 ?
#205000000
1"
1.
b1 <
b10011 =
b000000000111011101110 >
#210000000
0"
0.
#215000000
1"
1.
b10 <
b10010 =
#220000000
0"
0.
#225000000
1"
1.
b0 <
b1011 =
#230000000
0"
0.
#235000000
1"
1,
1.
19
b1010 =
#240000000
0"
0.
#245000000
1"
1.
b1001 =
#250000000
0"
0.
#255000000
1"
1.
b1000 =
#260000000
0"
0.
#265000000
1"
0,
1.
09
b1 <
b111 =
#270000000
0"
0.
#275000000
1"
1,
1.
19
b0 <
b110 =
#280000000
0"
0.
#285000000
1"
1.
b101 =
#290000000
0"
0.
#295000000
1"
1.
b100 =
#300000000
0"
0.
#305000000
1"
0,
1.
09
b1 <
b11 =
#310000000
0"
0.
#315000000
1"
1,
1.
19
b0 <
b10 =
#320000000
0"
0.
#325000000
1"
1.
b1 =
#330000000
0"
0.
#335000000
1"
1.
b0 =
#340000000
0"
0.
#345000000
1"
0,
1.
09
b1 ;
b1 <
b10100 =
#350000000
0"
0.
b0011111111 ?
#355000000
1"
1.
b10 <
b10011 =
b000001110111011101110 >
#360000000
0"
0.
#365000000
1"
1.
b0 <
b1111 =
#370000000
0"
0.
#375000000
1"
1,
1.
19
b1110 =
#380000000
0"
0.
#385000000
1"
1.
b1101 =
#390000000
0"
0.
#395000000
1"
1.
b1100 =
#400000000
0"
0.
#405000000
1"
0,
1.
09
b1 <
b1011 =
#410000000
0"
0.
#415000000
1"
1,
1.
19
b0 <
b1010 =
#420000000
0"
0.
#425000000
1"
1.
b1001 =
#430000000
0"
0.
#435000000
1"
1.
b1000 =
#440000000
0"
0.
#445000000
1"
0,
1.
09
b1 <
b111 =
#450000000
0"
0.
#455000000
1"
1,
1.
19
b0 <
b110 =
#460000000
0"
0.
#465000000
1"
1.
b101 =
#470000000
0"
0.
#475000000
1"
1.
b100 =
#480000000
0"
0.
#485000000
1"
0,
1.
09
b1 <
b11 =
#490000000
0"
0.
#495000000
1"
1,
1.
19
b0 <
b10 =
#500000000
0"
0.
#505000000
1"
1.
b1 =
#510000000
0"
0.
#515000000
1"
1.
b0 =
#520000000
0"
0.
#525000000
1"
0,
1.
09
b10 ;
b1 <
b10100 =
#530000000
0"
0.
b1111111111 ?
#535000000
1"
1.
b10 <
b10011 =
b011101110111011101110 >
#540000000
0"
0.
#545000000
1"
1,
1.
19
b0 <
b10010 =
#550000000
0"
0.
#555000000
1"
1.
b10001 =
#560000000
0"
0.
#565000000
1"
1.
b10000 =
#570000000
0"
0.
#575000000
1"
0,
1.
09
b1 <
b1111 =
#580000000
0"
0.
#585000000
1"
1,
1.
19
b0 <
b1110 =
#590000000
0"
0.
#595000000
1"
1.
b1101 =
#600000000
0"
0.
#605000000
1"
1.
b1100 =
#610000000
0"
0.
#615000000
1"
0,
1.
09
b1 <
b1011 =
#620000000
0"
0.
#625000000
1"
1,
1.
19
b0 <
b1010 =
#630000000
0"
0.
#635000000
1"
1.
b1001 =
#640000000
0"
0.
#645000000
1"
1.
b1000 =
#650000000
0"
0.
#655000000
1"
0,
1.
09
b1 <
b111 =
#660000000
0"
0.
#665000000
1"
1,
1.
19
b0 <
b110 =
#670000000
0"
0.
#675000000
1"
1.
b101 =
#680000000
0"
0.
#685000000
1"
1.
b100 =
#690000000
0"
0.
#695000000
1"
0,
1.
09
b1 <
b11 =
#700000000
0"
0.
#705000000
1"
1,
1.
19
b0 <
b10 =
#710000000
0"
0.
#715000000
1"
1.
b1 =
#720000000
0"
0.
#725000000
1"
1.
b0 =
#730000000
0"
0.
#735000000
1"
0,
1.
09
b11 ;
b1 <
b10100 =
#740000000
0"
0.
#745000000
1"
1.
b10 <
b10011 =
#750000000
0"
0.
#755000000
1"
1,
1.
19
b0 <
b10010 =
#760000000
0"
0.
#765000000
1"
1.
b10001 =
#770000000
0"
0.
#775000000
1"
1.
b10000 =
#780000000
0"
0.
#785000000
1"
0,
1.
09
b1 <
b1111 =
#790000000
0"
0.
#795000000
1"
1,
1.
19
b0 <
b1110 =
#800000000
0"
0.
#805000000
1"
1.
b1101 =
#810000000
0"
0.
#815000000
1"
1.
b1100 =
#820000000
0"
0.
#825000000
1"
0,
1.
09
b1 <
b1011 =
#830000000
0"
0.
#835000000
1"
1,
1.
19
b0 <
b1010 =
#840000000
0"
0.
#845000000
1"
1.
b1001 =
#850000000
0"
0.
#855000000
1"
1.
b1000 =
#860000000
0"
0.
#865000000
1"
0,
1.
09
b1 <
b111 =
#870000000
0"
0.
#875000000
1"
1,
1.
19
b0 <
b110 =
#880000000
0"
0.
#885000000
1"
1.
b101 =
#890000000
0"
0.
#895000000
1"
1.
b100 =
#900000000
0"
0.
#905000000
1"
0,
1.
09
b1 <
b11 =
#910000000
0"
0.
#915000000
1"
1,
1.
19
b0 <
b10 =
#920000000
0"
0.
#925000000
1"
1.
b1 =
#930000000
0"
0.
#935000000
1"
1.
b0 =
#940000000
0"
0.
#945000000
1"
0,
1.
09
b100 ;
b1 <
b10100 =
#950000000
0"
0.
b0000110101 ?
#955000000
1"
1.
b10 <
b10011 =
b000000000111000100010 >
#960000000
0"
0.
#965000000
1"
1.
b0 <
b1011 =
#970000000
0"
0.
#975000000
1"
1,
1.
19
b1010 =
#980000000
0"
0.
#985000000
1"
1.
b1001 =
#990000000
0"
0.
#995000000
1"
1.
b1000 =
#1000000000
0"
0.
#1005000000
1"
0,
1.
09
b1 <
b111 =
#1010000000
0"
0.
#1015000000
1"
1.
b10 <
b110 =
#1020000000
0"
0.
#1025000000
1"
1.
b0 <
b101 =
#1030000000
0"
0.
#1035000000
1"
1,
1.
19
b100 =
#1040000000
0"
0.
#1045000000
1"
0,
1.
09
b1 <
b11 =
#1050000000
0"
0.
#1055000000
1"
1.
b10 <
b10 =
#1060000000
0"
0.
#1065000000
1"
1.
b0 <
b1 =
#1070000000
0"
0.
#1075000000
1"
1,
1.
19
b0 =
#1080000000
0"
0.
#1085000000
1"
0,
1.
09
b101 ;
b1 <
b10100 =
#1090000000
0"
0.
b0000000111 ?
#1095000000
1"
1.
b10 <
b10011 =
b000000000000000101110 >
#1100000000
0"
0.
#1105000000
1"
1.
b0 <
#1110000000
0"
0.
#1115000000
1"
1.
b1 <
b10010 =
#1120000000
0"
0.
#1125000000
1"
1.
b10 <
b10001 =
#1130000000
0"
0.
#1135000000
1"
1.
b0 <
b101 =
#1140000000
0"
0.
#1145000000
1"
1,
1.
19
b100 =
#1150000000
0"
0.
#1155000000
1"
0,
1.
09
b1 <
b11 =
#1160000000
0"
0.
#1165000000
1"
1,
1.
19
b0 <
b10 =
#1170000000
0"
0.
#1175000000
1"
1.
b1 =
#1180000000
0"
0.
#1185000000
1"
1.
b0 =
#1190000000
0"
0.
#1195000000
1"
0,
1.
09
b110 ;
b1 <
b10100 =
#1200000000
0"
0.
b0001110101 ?
#1205000000
1"
1.
b10 <
b10011 =
b000000010111000100010 >
#1210000000
0"
0.
#1215000000
1"
1.
b0 <
b1101 =
#1220000000
0"
0.
#1225000000
1"
1,
1.
19
b1100 =
#1230000000
0"
0.
#1235000000
1"
0,
1.
09
b1 <
b1011 =
#1240000000
0"
0.
#1245000000
1"
1,
1.
19
b0 <
b1010 =
#1250000000
0"
0.
#1255000000
1"
1.
b1001 =
#1260000000
0"
0.
#1265000000
1"
1.
b1000 =
#1270000000
0"
0.
#1275000000
1"
0,
1.
09
b1 <
b111 =
#1280000000
0"
0.
#1285000000
1"
1.
b10 <
b110 =
#1290000000
0"
0.
#1295000000
1"
1.
b0 <
b101 =
#1300000000
0"
0.
#1305000000
1"
1,
1.
19
b100 =
#1310000000
0"
0.
#1315000000
1"
0,
1.
09
b1 <
b11 =
#1320000000
0"
0.
#1325000000
1"
1.
b10 <
b10 =
#1330000000
0"
0.
#1335000000
1"
1.
b0 <
b1 =
#1340000000
0"
0.
#1345000000
1"
1,
1.
19
b0 =
#1350000000
0"
0.
#1355000000
1"
0,
1.
09
b111 ;
b1 <
b10100 =
#1360000000
0"
0.
b0001010111 ?
#1365000000
1"
1.
b10 <
b10011 =
b000000010001000101110 >
#1370000000
0"
0.
#1375000000
1"
1.
b0 <
b1101 =
#1380000000
0"
0.
#1385000000
1"
1,
1.
19
b1100 =
#1390000000
0"
0.
#1395000000
1"
0,
1.
09
b1 <
b1011 =
#1400000000
0"
0.
#1405000000
1"
1.
b10 <
b1010 =
#1410000000
0"
0.
#1415000000
1"
1.
b0 <
b1001 =
#1420000000
0"
0.
#1425000000
1"
1,
1.
19
b1000 =
#1430000000
0"
0.
#1435000000
1"
0,
1.
09
b1 <
b111 =
#1440000000
0"
0.
#1445000000
1"
1.
b10 <
b110 =
#1450000000
0"
0.
#1455000000
1"
1.
b0 <
b101 =
#1460000000
0"
0.
#1465000000
1"
1,
1.
19
b100 =
#1470000000
0"
0.
#1475000000
1"
0,
1.
09
b1 <
b11 =
#1480000000
0"
0.
#1485000000
1"
1,
1.
19
b0 <
b10 =
#1490000000
0"
0.
#1495000000
1"
1.
b1 =
#1500000000
0"
0.
#1505000000
1"
1.
b0 =
#1510000000
0"
0.
#1515000000
1"
0,
1.
09
b1000 ;
b1 <
b10100 =
#1520000000
0"
1-
0.
1:
b0000000000 ?
#1525000000
1"
1.
b000000000000000000000 >
