extra/mux_10bit_driver.vhd
library ieee;
  use ieee.std_logic_1164.all;
  use ieee.numeric_std.all;


entity mux_10bit_driver is
    port(
    clk         : in  std_logic;
    rst         : in  std_logic;
    input       : in  std_logic_vector(9 downto 0);
    output1      : out  std_logic_vector(9 downto 0);
    output2      : out  std_logic_vector(9 downto 0);
    output3      : out  std_logic_vector(9 downto 0);
    output4      : out  std_logic_vector(9 downto 0);
    output5      : out  std_logic_vector(9 downto 0);
    output6      : out  std_logic_vector(9 downto 0);
    output7      : out  std_logic_vector(9 downto 0);
    output8      : out  std_logic_vector(9 downto 0)
    );
end entity mux_10bit_driver;

architecture Behavioral of mux_10bit_driver is
    signal sig_control : std_logic_vector(9 downto 0) := "0000000000";
    signal sig_1 : std_logic_vector(9 downto 0) := "0000000000";
    signal sig_2 : std_logic_vector(9 downto 0) := "0000000000";
    signal sig_3 : std_logic_vector(9 downto 0) := "0000000000";
    signal sig_4 : std_logic_vector(9 downto 0) := "0000000000";
    signal sig_5 : std_logic_vector(9 downto 0) := "0000000000";
    signal sig_6 : std_logic_vector(9 downto 0) := "0000000000";
    signal sig_7 : std_logic_vector(9 downto 0) := "0000000000";
    signal sig_8 : std_logic_vector(9 downto 0) := "0000000000";
    begin
        p_mux_10bit_driver : process (clk,input) is
            begin
                if (rst = '1') then
                    output1 <= "0000000000";
                    output2 <= "0000000000";
                    output3 <= "0000000000";
                    output4 <= "0000000000";
                    output5 <= "0000000000";
                    output6 <= "0000000000";
                    output7 <= "0000000000";
                    output8 <= "0000000000";
                    sig_1   <= "0000000000";
                    sig_2   <= "0000000000";
                    sig_3   <= "0000000000";
                    sig_4   <= "0000000000";
                    sig_5   <= "0000000000";
                    sig_6   <= "0000000000";
                    sig_7   <= "0000000000";
                elsif rising_edge(clk) then
                    if input /= sig_control then
                        sig_8 <= sig_7;
                        sig_7 <= sig_6;
                        sig_6 <= sig_5;
                        sig_5 <= sig_4;
                        sig_4 <= sig_3;
                        sig_3 <= sig_2;
                        sig_2 <= sig_1;
                        sig_1 <= input;
                        output1 <= input;
                        output2 <= sig_1;
                        output3 <= sig_2;
                        output4 <= sig_3;
                        output5 <= sig_4;
                        output6 <= sig_5;
                        output7 <= sig_6;
                        output8 <= sig_7;
                        sig_control <= input;
                    end if;
                end if;
            end process p_mux_10bit_driver;
    end architecture Behavioral;

extra/tb_mux_10bit_driver.vhd
library ieee;
  use ieee.std_logic_1164.all;
  use ieee.numeric_std.all;


entity tb_mux_10bit_driver is
--  Port ( );
end tb_mux_10bit_driver;

architecture testbench of tb_mux_10bit_driver is

    constant c_CLK_100MHZ_PERIOD : time := 10 ns;

    signal rst               : std_logic;
    signal sig_clk_100mhz    : std_logic;
    signal input             : std_logic_vector(9 downto 0);
    signal output1           : std_logic_vector(9 downto 0);
    signal output2           : std_logic_vector(9 downto 0);
    signal output3           : std_logic_vector(9 downto 0);
    signal output4           : std_logic_vector(9 downto 0);
    signal output5           : std_logic_vector(9 downto 0);
    signal output6           : std_logic_vector(9 downto 0);
    signal output7           : std_logic_vector(9 downto 0);
    signal output8           : std_logic_vector(9 downto 0);


begin
    uut_mux_10bit_driver: entity work.mux_10bit_driver
        port map(
            rst        => rst,
            clk        => sig_clk_100mhz,
            input      => input,
            output1    => output1,
            output2    => output2,
            output3    => output3,
            output4    => output4,
            output5    => output5,
            output6    => output6,
            output7    => output7,
            output8    => output8
        );
        
    p_clk_gen : process is
    begin
          
        while now < 1000 ns loop -- 100 periods of 100MHz clock
          
             sig_clk_100mhz <= '0';
             wait for c_CLK_100MHZ_PERIOD / 2;
             sig_clk_100mhz <= '1';
             wait for c_CLK_100MHZ_PERIOD / 2;
          
        end loop;
        wait;
          
    end process p_clk_gen;

    p_reset_gen : process is
    begin
      
        rst <= '0';
        wait for 10 ns;
        rst <= '1';
        wait for 90 ns;
        rst <= '0';
        wait for 10 ns;
        wait;
      
    end process p_reset_gen;


    p_stimulus : process
    begin
        input <= "0000001101";
        wait for 50 ns;
    	input <= "0000010111";
        wait for 200 ns;
        input <= "0000011101";
        wait for 100 ns;
        input <= "0000000101";
        wait for 100 ns;
        input <= "0000110111";
        wait for 100 ns;
        input <= "0001110101";
        wait for 100 ns;
        input <= "0000111111";
        wait for 100 ns;
        input <= "0001010111";
        wait for 100 ns;
        input <= "0000000001";
        wait for 100 ns;
        wait;
    end process p_stimulus;
end architecture testbench;

extra/waveforms/mux_10bit_driver.vcd
$date
  Mon Apr 17 08:06:08 2023
$end
$version
  GHDL v0
$end
$timescale
  1 fs
$end
$scope module standard $end
$upscope $end
$scope module std_logic_1164 $end
$upscope $end
$scope module numeric_std $end
$upscope $end
$scope module tb_mux_10bit_driver $end
$var reg 1 ! rst $end
$var reg 1 " sig_clk_100mhz $end
$var reg 10 # input[9:0] $end
$var reg 10 $ output1[9:0] $end
$var reg 10 % output2[9:0] $end
$var reg 10 & output3[9:0] $end
$var reg 10 ' output4[9:0] $end
$var reg 10 ( output5[9:0] $end
$var reg 10 ) output6[9:0] $end
$var reg 10 * output7[9:0] $end
$var reg 10 + output8[9:0] $end
$scope module uut_mux_10bit_driver $end
$var reg 1 , clk $end
$var reg 1 - rst $end
$var reg 10 . input[9:0] $end
$var reg 10 / output1[9:0] $end
$var reg 10 0 output2[9:0] $end
$var reg 10 1 output3[9:0] $end
$var reg 10 2 output4[9:0] $end
$var reg 10 3 output5[9:0] $end
$var reg 10 4 output6[9:0] $end
$var reg 10 5 output7[9:0] $end
$var reg 10 6 output8[9:0] $end
$var reg 10 7 sig_control[9:0] $end
$var reg 10 8 sig_1[9:0] $end
$var reg 10 9 sig_2[9:0] $end
$var reg 10 : sig_3[9:0] $end
$var reg 10 ; sig_4[9:0] $end
$var reg 10 < sig_5[9:0] $end
$var reg 10 = sig_6[9:0] $end
$var reg 10 > sig_7[9:0] $end
$var reg 10 ? sig_8[9:0] $end
$upscope $end
$upscope $end
$enddefinitions $end
#0
0!
0"
b0000001101 #
bUUUUUUUUUU $
bUUUUUUUUUU %
bUUUUUUUUUU &
bUUUUUUUUUU '
bUUUUUUUUUU (
bUUUUUUUUUU )
bUUUUUUUUUU *
bUUUUUUUUUU +
0,
0-
b0000001101 .
bUUUUUUUUUU /
bUUUUUUUUUU 0
bUUUUUUUUUU 1
bUUUUUUUUUU 2
bUUUUUUUUUU 3
bUUUUUUUUUU 4
bUUUUUUUUUU 5
bUUUUUUUUUU 6
b0000000000 7
b0000000000 8
b0000000000 9
b0000000000 :
b0000000000 ;
b0000000000 <
b0000000000 =
b0000000000 >
b0000000000 ?
#5000000
1"
b0000001101 $
b0000000000 %
b0000000000 &
b0000000000 '
b0000000000 (
b0000000000 )
b0000000000 *
b0000000000 +
1,
b0000001101 /
b0000000000 0
b0000000000 1
b0000000000 2
b0000000000 3
b0000000000 4
b0000000000 5
b0000000000 6
b0000001101 7
b0000001101 8
#10000000
1!
0"
b0000000000 $
0,
1-
b0000000000 /
b0000000000 8
#15000000
1"
1,
#20000000
0"
0,
#25000000
1"
1,
#30000000
0"
0,
#35000000
1"
1,
#40000000
0"
0,
#45000000
1"
1,
#50000000
0"
b0000010111 #
0,
b0000010111 .
#55000000
1"
1,
#60000000
0"
0,
#65000000
1"
1,
#70000000
0"
0,
#75000000
1"
1,
#80000000
0"
0,
#85000000
1"
1,
#90000000
0"
0,
#95000000
1"
1,
#100000000
0!
0"
0,
0-
#105000000
1"
b0000010111 $
1,
b0000010111 /
b0000010111 7
b0000010111 8
#110000000
0"
0,
#115000000
1"
1,
#120000000
0"
0,
#125000000
1"
1,
#130000000
0"
0,
#135000000
1"
1,
#140000000
0"
0,
#145000000
1"
1,
#150000000
0"
0,
#155000000
1"
1,
#160000000
0"
0,
#165000000
1"
1,
#170000000
0"
0,
#175000000
1"
1,
#180000000
0"
0,
#185000000
1"
1,
#190000000
0"
0,
#195000000
1"
1,
#200000000
0"
0,
#205000000
1"
1,
#210000000
0"
0,
#215000000
1"
1,
#220000000
0"
0,
#225000000
1"
1,
#230000000
0"
0,
#235000000
1"
1,
#240000000
0"
0,
#245000000
1"
1,
#250000000
0"
b0000011101 #
0,
b0000011101 .
#255000000
1"
b0000011101 $
b0000010111 %
1,
b0000011101 /
b0000010111 0
b0000011101 7
b0000011101 8
b0000010111 9
#260000000
0"
0,
#265000000
1"
1,
#270000000
0"
0,
#275000000
1"
1,
#280000000
0"
0,
#285000000
1"
1,
#290000000
0"
0,
#295000000
1"
1,
#300000000
0"
0,
#305000000
1"
1,
#310000000
0"
0,
#315000000
1"
1,
#320000000
0"
0,
#325000000
1"
1,
#330000000
0"
0,
#335000000
1"
1,
#340000000
0"
0,
#345000000
1"
1,
#350000000
0"
b0000000101 #
0,
b0000000101 .
#355000000
1"
b0000000101 $
b0000011101 %
b0000010111 &
1,
b0000000101 /
b0000011101 0
b0000010111 1
b0000000101 7
b0000000101 8
b0000011101 9
b0000010111 :
#360000000
0"
0,
#365000000
1"
1,
#370000000
0"
0,
#375000000
1"
1,
#380000000
0"
0,
#385000000
1"
1,
#390000000
0"
0,
#395000000
1"
1,
#400000000
0"
0,
#405000000
1"
1,
#410000000
0"
0,
#415000000
1"
1,
#420000000
0"
0,
#425000000
1"
1,
#430000000
0"
0,
#435000000
1"
1,
#440000000
0"
0,
#445000000
1"
1,
#450000000
0"
b0000110111 #
0,
b0000110111 .
#455000000
1"
b0000110111 $
b0000000101 %
b0000011101 &
b0000010111 '
1,
b0000110111 /
b0000000101 0
b0000011101 1
b0000010111 2
b0000110111 7
b0000110111 8
b0000000101 9
b0000011101 :
b0000010111 ;
#460000000
0"
0,
#465000000
1"
1,
#470000000
0"
0,
#475000000
1"
1,
#480000000
0"
0,
#485000000
1"
1,
#490000000
0"
0,
#495000000
1"
1,
#500000000
0"
0,
#505000000
1"
1,
#510000000
0"
0,
#515000000
1"
1,
#520000000
0"
0,
#525000000
1"
1,
#530000000
0"
0,
#535000000
1"
1,
#540000000
0"
0,
#545000000
1"
1,
#550000000
0"
b0001110101 #
0,
b0001110101 .
#555000000
1"
b0001110101 $
b0000110111 %
b0000000101 &
b0000011101 '
b0000010111 (
1,
b0001110101 /
b0000110111 0
b0000000101 1
b0000011101 2
b0000010111 3
b0001110101 7
b0001110101 8
b0000110111 9
b0000000101 :
b0000011101 ;
b0000010111 <
#560000000
0"
0,
#565000000
1"
1,
#570000000
0"
0,
#575000000
1"
1,
#580000000
0"
0,
#585000000
1"
1,
#590000000
0"
0,
#595000000
1"
1,
#600000000
0"
0,
#605000000
1"
1,
#610000000
0"
0,
#615000000
1"
1,
#620000000
0"
0,
#625000000
1"
1,
#630000000
0"
0,
#635000000
1"
1,
#640000000
0"
0,
#645000000
1"
1,
#650000000
0"
b0000111111 #
0,
b0000111111 .
#655000000
1"
b0000111111 $
b0001110101 %
b0000110111 &
b0000000101 '
b0000011101 (
b0000010111 )
1,
b0000111111 /
b0001110101 0
b0000110111 1
b0000000101 2
b0000011101 3
b0000010111 4
b0000111111 7
b0000111111 8
b0001110101 9
b0000110111 :
b0000000101 ;
b0000011101 <
b0000010111 =
#660000000
0"
0,
#665000000
1"
1,
#670000000
0"
0,
#675000000
1"
1,
#680000000
0"
0,
#685000000
1"
1,
#690000000
0"
0,
#695000000
1"
1,
#700000000
0"
0,
#705000000
1"
1,
#710000000
0"
0,
#715000000
1"
1,
#720000000
0"
0,
#725000000
1"
1,
#730000000
0"
0,
#735000000
1"
1,
#740000000
0"
0,
#745000000
1"
1,
#750000000
0"
b0001010111 #
0,
b0001010111 .
#755000000
1"
b0001010111 $
b0000111111 %
b0001110101 &
b0000110111 '
b0000000101 (
b0000011101 )
b0000010111 *
1,
b0001010111 /
b0000111111 0
b0001110101 1
b0000110111 2
b0000000101 3
b0000011101 4
b0000010111 5
b0001010111 7
b0001010111 8
b0000111111 9
b0001110101 :
b0000110111 ;
b0000000101 <
b0000011101 =
b0000010111 >
#760000000
0"
0,
#765000000
1"
1,
#770000000
0"
0,
#775000000
1"
1,
#780000000
0"
0,
#785000000
1"
1,
#790000000
0"
0,
#795000000
1"
1,
#800000000
0"
0,
#805000000
1"
1,
#810000000
0"
0,
#815000000
1"
1,
#820000000
0"
0,
#825000000
1"
1,
#830000000
0"
0,
#835000000
1"
1,
#840000000
0"
0,
#845000000
1"
1,
#850000000
0"
b0000000001 #
0,
b0000000001 .
#855000000
1"
b0000000001 $
b0001010111 %
b0000111111 &
b0001110101 '
b0000110111 (
b0000000101 )
b0000011101 *
b0000010111 +
1,
b0000000001 /
b0001010111 0
b0000111111 1
b0001110101 2
b0000110111 3
b0000000101 4
b0000011101 5
b0000010111 6
b0000000001 7
b0000000001 8
b0001010111 9
b0000111111 :
b0001110101 ;
b0000110111 <
b0000000101 =
b0000011101 >
b0000010111 ?
