extra/switch_driver.vhd
library ieee;
  use ieee.std_logic_1164.all;
  use ieee.numeric_std.all;


entity switch_driver is
    port(
    clk         : in  std_logic;
    rst         : in  std_logic;
    send        : in std_logic;
    SW          : in  std_logic_vector(9 downto 0);
    output      : out  std_logic_vector(9 downto 0)
    );
end entity switch_driver;

architecture Behavioral of switch_driver is
    signal sig_control : std_logic_vector(9 downto 0) := "0000000000";
    begin
        p_switch_driver : process (clk,send) is
            begin
                if (rst = '1') then
                    output        <= "0000000000";
                    sig_control   <= "0000000000";
                elsif rising_edge(clk) then
                    if (send = '1') then
                        sig_control(0) <= SW(0);
                        sig_control(1) <= SW(1);
                        sig_control(2) <= SW(2);
                        sig_control(3) <= SW(3);
                        sig_control(4) <= SW(4);
                        sig_control(5) <= SW(5);
                        sig_control(6) <= SW(6);
                        sig_control(7) <= SW(7);
                        sig_control(8) <= SW(8);
                        sig_control(9) <= SW(9);
                        output <= sig_control;
                    end if;
                end if;
            end process p_switch_driver;
    end architecture Behavioral;

extra/tb_switch_driver.vhd
library ieee;
  use ieee.std_logic_1164.all;
  use ieee.numeric_std.all;


entity tb_switch_driver is
--  Port ( );
end tb_switch_driver;

architecture testbench of tb_switch_driver is

    constant c_CLK_100MHZ_PERIOD : time := 10 ns;

    signal rst               : std_logic;
    signal sig_clk_100mhz    : std_logic;
    signal send              : std_logic;
    signal SW                : std_logic_vector(9 downto 0);
    signal output            : std_logic_vector(9 downto 0);


begin
    uut_switch_driver: entity work.switch_driver
        port map(
            rst        => rst,
            clk        => sig_clk_100mhz,
            send       => send,
            SW         => SW,
            output     => output
        );
        
    p_clk_gen : process is
    begin
          
        while now < 1200 ns loop -- 100 periods of 100MHz clock
          
             sig_clk_100mhz <= '0';
             wait for c_CLK_100MHZ_PERIOD / 2;
             sig_clk_100mhz <= '1';
             wait for c_CLK_100MHZ_PERIOD / 2;
          
        end loop;
        wait;
          
    end process p_clk_gen;

    p_reset_gen : process is
    begin
      
        rst <= '0';
        wait for 10 ns;
        rst <= '1';
        wait for 90 ns;
        rst <= '0';
        wait for 10 ns;
        wait;
      
    end process p_reset_gen;


    p_stimulus : process
    begin
        SW <= "0000001101";
        send <= '0';
        wait for 20 ns;
        send <= '1';
        wait for 10 ns;
        send <= '0';
        wait for 50 ns;
    	SW <= "0000010111";
        wait for 20 ns;
        send <= '1';
        wait for 10 ns;
        send <= '0';
        wait for 200 ns;
        SW <= "0000011101";
        wait for 20 ns;
        send <= '1';
        wait for 10 ns;
        send <= '0';
        wait for 100 ns;
        SW <= "0000000101";
        wait for 20 ns;
        send <= '1';
        wait for 10 ns;
        send <= '0';
        wait for 100 ns;
        SW <= "0000110111";
        wait for 20 ns;
        send <= '1';
        wait for 10 ns;
        send <= '0';
        wait for 100 ns;
        SW <= "0001110101";
        wait for 20 ns;
        send <= '1';
        wait for 10 ns;
        send <= '0';
        wait for 100 ns;
        SW <= "0000111111";
        wait for 20 ns;
        send <= '1';
        wait for 10 ns;
        send <= '0';
        wait for 100 ns;
        SW <= "0001010111";
        wait for 20 ns;
        send <= '1';
        wait for 10 ns;
        send <= '0';
        wait for 100 ns;
        SW <= "0000000001";
        wait for 20 ns;
        send <= '1';
        wait for 10 ns;
        send <= '0';
        wait for 100 ns;
        wait;
    end process p_stimulus;
end architecture testbench;

extra/waveforms/switch_driver.vcd
$date
  Mon Apr 17 08:16:53 2023
$end
$version
  GHDL v0
$end
$timescale
  1 fs
$end
$scope module standard $end
$upscope $end
$scope module std_logic_1164 $end
$upscope $end
$scope module numeric_std $end
$upscope $end
$scope module tb_switch_driver $end
$var reg 1 ! rst $end
$var reg 1 " sig_clk_100mhz $end
$var reg 1 # send $end
$var reg 10 $ sw[9:0] $end
$var reg 10 % output[9:0] $end
$scope module uut_switch_driver $end
$var reg 1 & clk $end
$var reg 1 ' rst $end
$var reg 1 ( send $end
$var reg 10 ) sw[9:0] $end
$var reg 10 * output[9:0] $end
$var reg 10 + sig_control[9:0] $end
$upscope $end
$upscope $end
$enddefinitions $end
#0
0!
0"
0#
b0000001101 $
bUUUUUUUUUU %
0&
0'
0(
b0000001101 )
bUUUUUUUUUU *
b0000000000 +
#5000000
1"
1&
#10000000
1!
0"
b0000000000 %
0&
1'
b0000000000 *
#15000000
1"
1&
#20000000
0"
1#
0&
1(
#25000000
1"
1&
#30000000
0"
0#
0&
0(
#35000000
1"
1&
#40000000
0"
0&
#45000000
1"
1&
#50000000
0"
0&
#55000000
1"
1&
#60000000
0"
0&
#65000000
1"
1&
#70000000
0"
0&
#75000000
1"
1&
#80000000
0"
b0000010111 $
0&
b0000010111 )
#85000000
1"
1&
#90000000
0"
0&
#95000000
1"
1&
#100000000
0!
0"
1#
0&
0'
1(
#105000000
1"
1&
b0000010111 +
#110000000
0"
0#
0&
0(
#115000000
1"
1&
#120000000
0"
0&
#125000000
1"
1&
#130000000
0"
0&
#135000000
1"
1&
#140000000
0"
0&
#145000000
1"
1&
#150000000
0"
0&
#155000000
1"
1&
#160000000
0"
0&
#165000000
1"
1&
#170000000
0"
0&
#175000000
1"
1&
#180000000
0"
0&
#185000000
1"
1&
#190000000
0"
0&
#195000000
1"
1&
#200000000
0"
0&
#205000000
1"
1&
#210000000
0"
0&
#215000000
1"
1&
#220000000
0"
0&
#225000000
1"
1&
#230000000
0"
0&
#235000000
1"
1&
#240000000
0"
0&
#245000000
1"
1&
#250000000
0"
0&
#255000000
1"
1&
#260000000
0"
0&
#265000000
1"
1&
#270000000
0"
0&
#275000000
1"
1&
#280000000
0"
0&
#285000000
1"
1&
#290000000
0"
0&
#295000000
1"
1&
#300000000
0"
0&
#305000000
1"
1&
#310000000
0"
b0000011101 $
0&
b0000011101 )
#315000000
1"
1&
#320000000
0"
0&
#325000000
1"
1&
#330000000
0"
1#
0&
1(
#335000000
1"
b0000010111 %
1&
b0000010111 *
b0000011101 +
#340000000
0"
0#
0&
0(
#345000000
1"
1&
#350000000
0"
0&
#355000000
1"
1&
#360000000
0"
0&
#365000000
1"
1&
#370000000
0"
0&
#375000000
1"
1&
#380000000
0"
0&
#385000000
1"
1&
#390000000
0"
0&
#395000000
1"
1&
#400000000
0"
0&
#405000000
1"
1&
#410000000
0"
0&
#415000000
1"
1&
#420000000
0"
0&
#425000000
1"
1&
#430000000
0"
0&
#435000000
1"
1&
#440000000
0"
b0000000101 $
0&
b0000000101 )
#445000000
1"
1&
#450000000
0"
0&
#455000000
1"
1&
#460000000
0"
1#
0&
1(
#465000000
1"
b0000011101 %
1&
b0000011101 *
b0000000101 +
#470000000
0"
0#
0&
0(
#475000000
1"
1&
#480000000
0"
0&
#485000000
1"
1&
#490000000
0"
0&
#495000000
1"
1&
#500000000
0"
0&
#505000000
1"
1&
#510000000
0"
0&
#515000000
1"
1&
#520000000
0"
0&
#525000000
1"
1&
#530000000
0"
0&
#535000000
1"
1&
#540000000
0"
0&
#545000000
1"
1&
#550000000
0"
0&
#555000000
1"
1&
#560000000
0"
0&
#565000000
1"
1&
#570000000
0"
b0000110111 $
0&
b0000110111 )
#575000000
1"
1&
#580000000
0"
0&
#585000000
1"
1&
#590000000
0"
1#
0&
1(
#595000000
1"
b0000000101 %
1&
b0000000101 *
b0000110111 +
#600000000
0"
0#
0&
0(
#605000000
1"
1&
#610000000
0"
0&
#615000000
1"
1&
#620000000
0"
0&
#625000000
1"
1&
#630000000
0"
0&
#635000000
1"
1&
#640000000
0"
0&
#645000000
1"
1&
#650000000
0"
0&
#655000000
1"
1&
#660000000
0"
0&
#665000000
1"
1&
#670000000
0"
0&
#675000000
1"
1&
#680000000
0"
0&
#685000000
1"
1&
#690000000
0"
0&
#695000000
1"
1&
#700000000
0"
b0001110101 $
0&
b0001110101 )
#705000000
1"
1&
#710000000
0"
0&
#715000000
1"
1&
#720000000
0"
1#
0&
1(
#725000000
1"
b0000110111 %
1&
b0000110111 *
b0001110101 +
#730000000
0"
0#
0&
0(
#735000000
1"
1&
#740000000
0"
0&
#745000000
1"
1&
#750000000
0"
0&
#755000000
1"
1&
#760000000
0"
0&
#765000000
1"
1&
#770000000
0"
0&
#775000000
1"
1&
#780000000
0"
0&
#785000000
1"
1&
#790000000
0"
0&
#795000000
1"
1&
#800000000
0"
0&
#805000000
1"
1&
#810000000
0"
0&
#815000000
1"
1&
#820000000
0"
0&
#825000000
1"
1&
#830000000
0"
b0000111111 $
0&
b0000111111 )
#835000000
1"
1&
#840000000
0"
0&
#845000000
1"
1&
#850000000
0"
1#
0&
1(
#855000000
1"
b0001110101 %
1&
b0001110101 *
b0000111111 +
#860000000
0"
0#
0&
0(
#865000000
1"
1&
#870000000
0"
0&
#875000000
1"
1&
#880000000
0"
0&
#885000000
1"
1&
#890000000
0"
0&
#895000000
1"
1&
#900000000
0"
0&
#905000000
1"
1&
#910000000
0"
0&
#915000000
1"
1&
#920000000
0"
0&
#925000000
1"
1&
#930000000
0"
0&
#935000000
1"
1&
#940000000
0"
0&
#945000000
1"
1&
#950000000
0"
0&
#955000000
1"
1&
#960000000
0"
b0001010111 $
0&
b0001010111 )
#965000000
1"
1&
#970000000
0"
0&
#975000000
1"
1&
#980000000
0"
1#
0&
1(
#985000000
1"
b0000111111 %
1&
b0000111111 *
b0001010111 +
#990000000
0"
0#
0&
0(
#995000000
1"
1&
#1000000000
0"
0&
#1005000000
1"
1&
#1010000000
0"
0&
#1015000000
1"
1&
#1020000000
0"
0&
#1025000000
1"
1&
#1030000000
0"
0&
#1035000000
1"
1&
#1040000000
0"
0&
#1045000000
1"
1&
#1050000000
0"
0&
#1055000000
1"
1&
#1060000000
0"
0&
#1065000000
1"
1&
#1070000000
0"
0&
#1075000000
1"
1&
#1080000000
0"
0&
#1085000000
1"
1&
#1090000000
0"
b0000000001 $
0&
b0000000001 )
#1095000000
1"
1&
#1100000000
0"
0&
#1105000000
1"
1&
#1110000000
0"
1#
0&
1(
#1115000000
1"
b0001010111 %
1&
b0001010111 *
b0000000001 +
#1120000000
0"
0#
0&
0(
